Workbook

Sheet 1. How To Use
A1: SQL Server Consolidation Readiness Assessment — How To Use
A2: NTT DATA | Bradesco Bank. Inventory and migration-tracking workbook. Tabs: 1) this guide, 2) Servers, 3) Databases, 4) Dashboard, 5) Glossary, plus 'Lists (Config)' for dropdown values.
A4: COLOR LEGEND
A5: Light yellow fill | B5: Data obtainable by TECHNICAL QUERY: run it against the instance with SSMS / SQL Server Management Studio, Management Tools or the technical inventory (e.g. Database Name, Compatibility Level, Version, State, Size, Last Backup, Drive, ServerID). Refresh from the source system, never type by assumption.
A6: White fill | B6: Data that must come from PEOPLE OR DOCUMENTS: technical owner, application owner, functional/technical documentation (e.g. Environment, Criticality, Owner, Use / Purpose, Migration Status, Recommendation, Notes).
A7: Light blue fill | B7: Pre-loaded real data or automatic formulas (e.g. '# Databases (auto)' on the Servers tab). Do not overwrite formulas.
A9: TAB 2 — SERVERS: WHAT GOES IN EACH COLUMN
A10: ServerID | B10: Unique ID generated by the template (SRV-001…). Mandatory. Never reuse or renumber once databases are linked to it.
A11: Server (Hostname) / IP / Location / Network / Engine / Edition | B11: Exported from the infrastructure inventory. Text as reported by the source; multiple IPs separated by line breaks. Correct only with confirmation from Infra.
A12: In Scope (MSSQL) | B12: Automatic formula: 'Yes' when the engine contains 'Microsoft SQL Server'. Do not type over it.
A13: Environment / Support Status / Criticality / HA-DR | B13: Choose from the dropdown (values maintained in 'Lists (Config)'). Source: technical owner or documentation. Use 'Pending validation' if unknown.
A14: Technical Owner / Business Owner | B14: Full name or team distribution list. Source: application owner / CMDB. Mandatory before migration planning.
A15: Server Access (Yes/No) | B15: Checklist: does the assessment team have working access to the server? Dropdown Yes/No. Mandatory.
A16: Reviewed (Yes/No) | B16: Checklist: has this server row been fully reviewed and validated? Dropdown Yes/No. Mandatory.
A17: # Databases (auto) | B17: Formula: counts rows on Tab 3 whose ServerID matches this server. Do not edit.
A18: # Migration-Ready DBs (auto) | B18: Formula: counts this server's databases whose Migration Status is in the 'Migration-Ready Statuses' list on 'Lists (Config)' (Lift and Shift, Rehost, Replatform). Do not edit.
A20: TAB 3 — DATABASES: WHAT GOES IN EACH COLUMN
A21: DatabaseID | B21: Unique ID generated by the template (DB-001…). Mandatory. One row = one database (duplicates from the source export were consolidated; sizes summed).
A22: ServerID (link to Tab 2) | B22: Dropdown with the ServerIDs from Tab 2. Mandatory to close the inventory: today it is blank because the source export did not state the hosting server. Fill with Infra/DBA (e.g. SELECT @@SERVERNAME per instance).
A23: Database Name / Compatibility Level / SQL Version / State / Size (MB) / Last Backup / Drive | B23: Technical facts from the SQL export (sys.databases, backup history). Size is the total of data + log files in MB. Last Backup format: yyyy-mm-dd hh:mm:ss.
A24: Environment / Criticality | B24: Dropdowns. Source: application owner / functional documentation. Mandatory for migration planning.
A25: Application / Functional Owner | B25: Person or team accountable for the application using this database. Mandatory.
A26: Use / Purpose | B26: Short free text describing what the database supports (e.g. 'Core wires processing', 'SSRS report catalog'). Source: application owner / functional documentation.
A27: Migration Status | B27: Dropdown (see Glossary): Lift and Shift, Rehost, Replatform, Refactor, Repurchase, Retain, Retire, Pending analysis, Blocked. Default is 'Pending analysis'. Lift and Shift / Rehost / Replatform count as migration-ready.
A28: Recommendation / Discovery Source / Notes | B28: Recommendation: dropdown (Keep, Upgrade, Consolidate, Migrate, Decommission, Investigate). Discovery Source: where the row's information came from. Notes: free text, keep audit remarks here.
A30: EXAMPLE ROW (Tab 3) | B30: DB-011 | SRV-019 | BBFB_WIRES | 130 | SQL Server 2016 | ONLINE | 272 | 2024-12-17 4:14:33 | C: | Production | Critical | Payments Team | Wire transfers processing | Lift and Shift | Migrate | Technical Owner | Validated with DBA on 2026-07-14
A32: MAINTENANCE RULES
A33: 1 | B33: Never delete rows with real data; use State = OFFLINE, Migration Status = Retire, or Notes to flag decommissioned items.
A34: 2 | B34: One row per database and per server engine. Before adding a row, check the name does not already exist (no duplicates).
A35: 3 | B35: New dropdown values are added only on 'Lists (Config)' — they propagate automatically to every tab.
A36: 4 | B36: Do not overwrite formula columns (In Scope, # Databases, # Migration-Ready DBs, Dashboard). They recalculate automatically.
A37: 5 | B37: Keep IDs stable and sequential (SRV-###, DB-###). If you add a database, use the next free DB number and pick its ServerID from the dropdown.
A38: 6 | B38: Every figure obtained from a person or document should be traceable: set Discovery Source and add the date/contact in Notes.
A39: 7 | B39: Weekly review: refresh the technical (yellow) columns from SSMS, then update the Yes/No checklists and Migration Status; the Dashboard updates itself.

Sheet Lists (Config)
A1: Value lists (edit here to update the dropdowns across all tabs)
A3: Environment | B3: Support Status | C3: Criticality | D3: HA / DR | E3: Recommendation | F3: Readiness | G3: Discovery Source | H3: In Scope (MSSQL) | I3: Migration Status | J3: Yes/No | K3: Migration-Ready Statuses
A4: Production | B4: Supported | C4: Critical | D4: Always On AG | E4: Keep | F4: Ready | G4: SQL Server Access | H4: Yes | I4: Lift and Shift | J4: Yes | K4: Lift and Shift
A5: Staging/UAT | B5: Extended Support | C5: High | D5: Failover Cluster | E5: Upgrade | F5: Ready with Remediation | G5: Infrastructure Team | H5: No | I5: Rehost | J5: No | K5: Rehost
A6: QA | B6: End of Support (EOS) | C6: Medium | D6: Mirroring | E6: Consolidate | F6: Needs Investigation | G6: Applications Team | H6: To confirm | I6: Replatform | K6: Replatform
A7: Development | B7: Unknown | C7: Low | D7: Log Shipping | E7: Migrate | F7: Not Recommended | G7: Technical Owner | I7: Refactor
A8: DR | B8: Pending validation | C8: Unknown | D8: None Detected | E8: Decommission | F8: Pending validation | G8: Functional Owner | I8: Repurchase
A9: Pending validation | C9: Pending validation | D9: Unknown | E9: Investigate | G9: Scope Framework Meeting | I9: Retain
D10: Pending validation | E10: Pending validation | G10: Other Team | I10: Retire
G11: Technical Documentation | I11: Pending analysis
G12: Other | I12: Blocked
G13: Linked Server SQL

Sheet 2. Servers
A1: ServerID | B1: Server (Hostname) | C1: IP | D1: Location | E1: Network | F1: Engine / Product | G1: Edition | H1: In Scope (MSSQL) | I1: Environment | J1: Support Status | K1: Criticality | L1: HA / DR | M1: Technical Owner | N1: Business Owner | O1: Discovery Source | P1: Server Access (Yes/No) | Q1: Reviewed (Yes/No) | R1: # Databases (auto) | S1: # Migration-Ready DBs (auto) | T1: Notes | U1: Notes (2)
A2: SRV-001 | B2: BACBFBSITE | C2: 172.26.6.10 172.26.6.11 172.26.6.12 | D2: Orlando | E2: DMZ | F2: MySQL Server 8.0 | G2: - | H2: =IF(ISNUMBER(SEARCH("Microsoft SQL Server",F2)),"Yes","No") -> No | I2: DR | O2: Infrastructure Team | P2: No | Q2: No | R2: =COUNTIF('3. Databases'!$B$2:$B$192,$A2) -> 0 | S2: {=SUMPRODUCT(('3. Databases'!$B$2:$B$192=$A2)*COUNTIF('Lists (Config)'!$K$4:$K$6,'3. Databases'!$R$2:$R$192))} -> 0 | T2: Non-MSSQL product detected
A3: SRV-002 | B3: BACBPTRANSDB1 | C3: 172.29.5.25 172.29.5.39 | D3: NAP | E3: DMZ | F3: Microsoft SQL Server 2016 (64-bit) | G3: Standard | H3: =IF(ISNUMBER(SEARCH("Microsoft SQL Server",F3)),"Yes","No") -> Yes | I3: Production | J3: End of Support (EOS) | K3: High | L3: DR | M3: IT Operations Team, Rena Silva | N3: Devs | O3: Infrastructure Team | P3: No | Q3: No | R3: =COUNTIF('3. Databases'!$B$2:$B$192,$A3) -> 40 | S3: {=SUMPRODUCT(('3. Databases'!$B$2:$B$192=$A3)*COUNTIF('Lists (Config)'!$K$4:$K$6,'3. Databases'!$R$2:$R$192))} -> 0 | T3: MSSQL detected | U3: The login is from an untrusted domain and cannot be used with Windows authentication (172.29.5.25) The server was not found (172.29.5.39)
A4: SRV-003 | B4: BACBPTRANSDB1 | C4: 172.29.5.25 172.29.5.39 | D4: NAP | E4: DMZ | F4: MongoDB 8.2.6 2008R2Plus SSL (64 bit) | G4: - | H4: =IF(ISNUMBER(SEARCH("Microsoft SQL Server",F4)),"Yes","No") -> No | I4: Production | J4: Unknown | K4: High | L4: DR | M4: IT Operations Team | O4: Infrastructure Team | P4: No | Q4: No | R4: =COUNTIF('3. Databases'!$B$2:$B$192,$A4) -> 0 | S4: {=SUMPRODUCT(('3. Databases'!$B$2:$B$192=$A4)*COUNTIF('Lists (Config)'!$K$4:$K$6,'3. Databases'!$R$2:$R$192))} -> 0 | T4: Duplicate
A5: SRV-004 | B5: BACBPTRANSDB1 | C5: 172.29.5.25 172.29.5.39 | D5: NAP | E5: DMZ | F5: MySQL Server 8.0 | G5: - | H5: =IF(ISNUMBER(SEARCH("Microsoft SQL Server",F5)),"Yes","No") -> No | I5: Production | J5: Unknown | K5: High | L5: DR | M5: IT Operations Team | O5: Infrastructure Team | P5: No | Q5: No | R5: =COUNTIF('3. Databases'!$B$2:$B$192,$A5) -> 0 | S5: {=SUMPRODUCT(('3. Databases'!$B$2:$B$192=$A5)*COUNTIF('Lists (Config)'!$K$4:$K$6,'3. Databases'!$R$2:$R$192))} -> 0 | T5: Duplicate
A6: SRV-005 | B6: BACNAPIT | C6: 10.198.5.190 | D6: NAP | E6: Server | F6: Microsoft SQL Server 2012 (64-bit) | G6: Express | H6: =IF(ISNUMBER(SEARCH("Microsoft SQL Server",F6)),"Yes","No") -> Yes | I6: Production | K6: High | L6: DR | M6: IT Operations Team | N6: IT Operations Team | O6: Infrastructure Team | P6: No | Q6: No | R6: =COUNTIF('3. Databases'!$B$2:$B$192,$A6) -> 0 | S6: {=SUMPRODUCT(('3. Databases'!$B$2:$B$192=$A6)*COUNTIF('Lists (Config)'!$K$4:$K$6,'3. Databases'!$R$2:$R$192))} -> 0 | T6: SQL installed; no business databases found. | U6: The server was not found
A7: SRV-007 | B7: BACSANSRV | C7: 10.198.5.131 10.198.5.132 | D7: NAP | E7: Server | F7: Microsoft SQL Server Compact 4.0 SP1 x64 ENU | G7: Express | H7: =IF(ISNUMBER(SEARCH("Microsoft SQL Server",F7)),"Yes","No") -> Yes | I7: Production | L7: DR | M7: IT Operations Team | O7: Infrastructure Team | P7: No | Q7: No | R7: =COUNTIF('3. Databases'!$B$2:$B$192,$A7) -> 0 | S7: {=SUMPRODUCT(('3. Databases'!$B$2:$B$192=$A7)*COUNTIF('Lists (Config)'!$K$4:$K$6,'3. Databases'!$R$2:$R$192))} -> 0 | T7: Duplicate | U7: Same server as SRV-006
A8: SRV-006 | B8: BACSANSRV | C8: 10.198.5.131 10.198.5.132 | D8: NAP | E8: Server | F8: Microsoft SQL Server 2017 (64-bit) | G8: Express | H8: =IF(ISNUMBER(SEARCH("Microsoft SQL Server",F8)),"Yes","No") -> Yes | I8: Production | K8: High | L8: DR | M8: IT Operations Team | N8: IT Operations Team | O8: Infrastructure Team | P8: Yes | Q8: No | R8: =COUNTIF('3. Databases'!$B$2:$B$192,$A8) -> 23 | S8: {=SUMPRODUCT(('3. Databases'!$B$2:$B$192=$A8)*COUNTIF('Lists (Config)'!$K$4:$K$6,'3. Databases'!$R$2:$R$192))} -> 0 | T8: SQL installed; no business databases found.
A9: SRV-008 | B9: BBFBDATAPARSER | C9: 10.198.5.214 | D9: NAP | E9: Server | F9: Microsoft SQL Server 2016 (64-bit) | G9: Standard | H9: =IF(ISNUMBER(SEARCH("Microsoft SQL Server",F9)),"Yes","No") -> Yes | I9: Production | K9: High | L9: DR | M9: IT Operations Team | O9: Infrastructure Team | P9: No | Q9: No | R9: =COUNTIF('3. Databases'!$B$2:$B$192,$A9) -> 0 | S9: {=SUMPRODUCT(('3. Databases'!$B$2:$B$192=$A9)*COUNTIF('Lists (Config)'!$K$4:$K$6,'3. Databases'!$R$2:$R$192))} -> 0 | T9: MSSQL detected | U9: Login failed for user
A10: SRV-009 | B10: BBFBDBVIEW | C10: 10.196.5.31 | D10: Orlando | E10: Server | F10: Microsoft SQL Server 2019 (64-bit) | G10: Standard | H10: =IF(ISNUMBER(SEARCH("Microsoft SQL Server",F10)),"Yes","No") -> Yes | I10: DR | J10: Supported | K10: High | L10: DR | M10: IT Operations Team | N10: Devs | O10: Infrastructure Team | P10: No | Q10: No | R10: =COUNTIF('3. Databases'!$B$2:$B$192,$A10) -> 0 | S10: {=SUMPRODUCT(('3. Databases'!$B$2:$B$192=$A10)*COUNTIF('Lists (Config)'!$K$4:$K$6,'3. Databases'!$R$2:$R$192))} -> 0 | T10: MSSQL detected | U10: Login failed for user
A11: SRV-010 | B11: BBFBINTRANET | C11: 10.198.5.141 10.198.5.140 | D11: NAP | E11: Server | F11: MySQL Server 8.0 | G11: - | H11: =IF(ISNUMBER(SEARCH("Microsoft SQL Server",F11)),"Yes","No") -> No | I11: Production | J11: Supported | K11: Medium | L11: DR | M11: IT Operations Team, Rena Silva | N11: Devs | O11: Infrastructure Team | P11: No | Q11: No | R11: =COUNTIF('3. Databases'!$B$2:$B$192,$A11) -> 0 | S11: {=SUMPRODUCT(('3. Databases'!$B$2:$B$192=$A11)*COUNTIF('Lists (Config)'!$K$4:$K$6,'3. Databases'!$R$2:$R$192))} -> 0 | T11: SQL installed; no business databases found.
A12: SRV-011 | B12: BB-FW-AP-001 | C12: 10.20.100.25 | D12: Coral Gables | E12: Server | F12: Microsoft SQL Server Compact 4.0 x64 ENU | G12: - | H12: =IF(ISNUMBER(SEARCH("Microsoft SQL Server",F12)),"Yes","No") -> Yes | I12: Production | K12: Medium | L12: DR | M12: IT Operations Team | O12: Infrastructure Team | P12: No | Q12: No | R12: =COUNTIF('3. Databases'!$B$2:$B$192,$A12) -> 0 | S12: {=SUMPRODUCT(('3. Databases'!$B$2:$B$192=$A12)*COUNTIF('Lists (Config)'!$K$4:$K$6,'3. Databases'!$R$2:$R$192))} -> 0 | T12: SQL installed; no business databases found. | U12: Login failed for user
A13: SRV-012 | B13: bb-vl-ap-051 | C13: 10.198.5.26 | D13: NAP | E13: Server | F13: Mariadb-server | G13: - | H13: =IF(ISNUMBER(SEARCH("Microsoft SQL Server",F13)),"Yes","No") -> No | I13: Production | L13: DR | M13: IT Operations Team | O13: Infrastructure Team | P13: No | Q13: No | R13: =COUNTIF('3. Databases'!$B$2:$B$192,$A13) -> 0 | S13: {=SUMPRODUCT(('3. Databases'!$B$2:$B$192=$A13)*COUNTIF('Lists (Config)'!$K$4:$K$6,'3. Databases'!$R$2:$R$192))} -> 0 | T13: Non-MSSQL product detected
A14: SRV-013 | B14: BB-VV-AP-004 | C14: 10.198.5.127 | D14: NAP | E14: Server | F14: Microsoft SQL Server 2019 (64-bit) | G14: Standard | H14: =IF(ISNUMBER(SEARCH("Microsoft SQL Server",F14)),"Yes","No") -> Yes | I14: Production | L14: DR | M14: IT Operations Team | O14: Infrastructure Team | P14: No | Q14: No | R14: =COUNTIF('3. Databases'!$B$2:$B$192,$A14) -> 0 | S14: {=SUMPRODUCT(('3. Databases'!$B$2:$B$192=$A14)*COUNTIF('Lists (Config)'!$K$4:$K$6,'3. Databases'!$R$2:$R$192))} -> 0 | T14: SQL installed; no business databases found. | U14: Login failed for user
A15: SRV-014 | B15: BB-VV-AP-009 | C15: 10.198.5.149 | D15: NAP | E15: Server | F15: Microsoft SQL Server 2019 (64-bit) | G15: Standard | H15: =IF(ISNUMBER(SEARCH("Microsoft SQL Server",F15)),"Yes","No") -> Yes | I15: Production | J15: Supported | K15: Medium | L15: DR | M15: IT Operations Team | N15: Finance | O15: Infrastructure Team | P15: No | Q15: No | R15: =COUNTIF('3. Databases'!$B$2:$B$192,$A15) -> 0 | S15: {=SUMPRODUCT(('3. Databases'!$B$2:$B$192=$A15)*COUNTIF('Lists (Config)'!$K$4:$K$6,'3. Databases'!$R$2:$R$192))} -> 0 | T15: MSSQL detected | U15: Login failed for user
A16: SRV-015 | B16: BB-VV-BD-001 | C16: 10.198.5.71 | D16: NAP | E16: Server | F16: Microsoft SQL Server 2019 (64-bit) | G16: Standard | H16: =IF(ISNUMBER(SEARCH("Microsoft SQL Server",F16)),"Yes","No") -> Yes | I16: Production | J16: Supported | K16: High | L16: DR | M16: IT Operations Team | N16: DataWarehouse | O16: Infrastructure Team | P16: Yes | Q16: No | R16: =COUNTIF('3. Databases'!$B$2:$B$192,$A16) -> 5 | S16: {=SUMPRODUCT(('3. Databases'!$B$2:$B$192=$A16)*COUNTIF('Lists (Config)'!$K$4:$K$6,'3. Databases'!$R$2:$R$192))} -> 0 | T16: MSSQL detected | U16: SQLEXPRESS - 2017 version detected
A17: SRV-042 | B17: BB-VV-BD-001 | C17: 10.198.5.71 | D17: NAP | E17: Server | F17: Microsoft SQL Server 2016 LocalDB | G17: Standard | H17: =IF(ISNUMBER(SEARCH("Microsoft SQL Server",F17)),"Yes","No") -> Yes | I17: Production | K17: Medium | L17: DR | M17: IT Operations Team | N17: DataWarehouse | O17: Infrastructure Team | P17: No | Q17: No | R17: =COUNTIF('3. Databases'!$B$2:$B$192,$A17) -> 0 | S17: {=SUMPRODUCT(('3. Databases'!$B$2:$B$192=$A17)*COUNTIF('Lists (Config)'!$K$4:$K$6,'3. Databases'!$R$2:$R$192))} -> 0 | T17: MSSQL detected | U17: Same as server SRV-015
A18: SRV-017 | B18: BB-VV-BD-004 | C18: 10.198.5.144 | D18: NAP | E18: Server | F18: Microsoft SQL Server 2019 (64-bit) | G18: Standard | H18: =IF(ISNUMBER(SEARCH("Microsoft SQL Server",F18)),"Yes","No") -> Yes | I18: Production | J18: Supported | K18: High | L18: DR | M18: IT Operations Team | N18: Operations Deparment | O18: Infrastructure Team | P18: No | Q18: No | R18: =COUNTIF('3. Databases'!$B$2:$B$192,$A18) -> 0 | S18: {=SUMPRODUCT(('3. Databases'!$B$2:$B$192=$A18)*COUNTIF('Lists (Config)'!$K$4:$K$6,'3. Databases'!$R$2:$R$192))} -> 0 | T18: MSSQL detected | U18: Login failed for user
A19: SRV-054 | B19: BB-VV-BD-005 | E19: Server | F19: Microsoft SQL Server 2019 (64-bit) | G19: Standard | H19: =IF(ISNUMBER(SEARCH("Microsoft SQL Server",F19)),"Yes","No") -> Yes | I19: Production | J19: Supported | K19: Medium | L19: DR | M19: IT Operations Team | N19: DataWarehouse | O19: Linked Server SQL | P19: No | Q19: No | R19: =COUNTIF('3. Databases'!$B$2:$B$192,$A19) -> 1 | S19: {=SUMPRODUCT(('3. Databases'!$B$2:$B$192=$A19)*COUNTIF('Lists (Config)'!$K$4:$K$6,'3. Databases'!$R$2:$R$192))} -> 0 | T19: MSSQL detected
A20: SRV-053 | B20: BB-VV-BD-006 | C20: 10.198.5.148 | D20: NAP | E20: Server | F20: Microsoft SQL Server 2022 (64-bit) | G20: Unknown | H20: =IF(ISNUMBER(SEARCH("Microsoft SQL Server",F20)),"Yes","No") -> Yes | I20: Production | J20: Supported | K20: Medium | L20: DR | M20: IT Operations Team | N20: DataWarehouse | O20: Other Team | P20: Yes | Q20: No | R20: =COUNTIF('3. Databases'!$B$2:$B$192,$A20) -> 6 | S20: {=SUMPRODUCT(('3. Databases'!$B$2:$B$192=$A20)*COUNTIF('Lists (Config)'!$K$4:$K$6,'3. Databases'!$R$2:$R$192))} -> 0 | T20: MSSQL detected
A21: SRV-056 | B21: BB-VV-BD-008 | E21: Server | F21: Microsoft SQL Server 2022 (64-bit) | G21: Unknown | H21: =IF(ISNUMBER(SEARCH("Microsoft SQL Server",F21)),"Yes","No") -> Yes | I21: Development | M21: Renan Silva | N21: Devs | O21: Linked Server SQL | P21: No | Q21: No | R21: =COUNTIF('3. Databases'!$B$2:$B$192,$A21) -> 5 | S21: {=SUMPRODUCT(('3. Databases'!$B$2:$B$192=$A21)*COUNTIF('Lists (Config)'!$K$4:$K$6,'3. Databases'!$R$2:$R$192))} -> 0 | T21: Linked Server from NiFi Dev
A22: SRV-018 | B22: BB-VV-DC-001 | C22: 10.198.5.69 10.198.5.134 10.198.5.192 | D22: NAP | E22: Server | F22: Microsoft SQL Server Compact 4.0 SP1 x64 ENU | G22: - | H22: =IF(ISNUMBER(SEARCH("Microsoft SQL Server",F22)),"Yes","No") -> Yes | I22: Production | K22: High | L22: DR | M22: IT Operations Team | N22: Infrastructure Team | O22: Infrastructure Team | P22: No | Q22: No | R22: =COUNTIF('3. Databases'!$B$2:$B$192,$A22) -> 0 | S22: {=SUMPRODUCT(('3. Databases'!$B$2:$B$192=$A22)*COUNTIF('Lists (Config)'!$K$4:$K$6,'3. Databases'!$R$2:$R$192))} -> 0 | T22: Non-MSSQL product detected | U22: The server was not found
A23: SRV-016 | B23: BB-VV-HV-001 | C23: 10.198.5.179 | D23: NAP | E23: Server | F23: Microsoft SQL Server 2016 (64-bit) | G23: Standard | H23: =IF(ISNUMBER(SEARCH("Microsoft SQL Server",F23)),"Yes","No") -> Yes | I23: Production | L23: DR | M23: IT Operations Team | O23: Infrastructure Team | P23: No | Q23: No | R23: =COUNTIF('3. Databases'!$B$2:$B$192,$A23) -> 0 | S23: {=SUMPRODUCT(('3. Databases'!$B$2:$B$192=$A23)*COUNTIF('Lists (Config)'!$K$4:$K$6,'3. Databases'!$R$2:$R$192))} -> 0 | T23: MSSQL detected | U23: Login failed for user
A24: SRV-020 | B24: BB-VV-HV-001 | C24: 10.198.5.179 | D24: NAP | E24: Server | F24: Microsoft SQL Server 2019 (64-bit) | G24: Standard | H24: =IF(ISNUMBER(SEARCH("Microsoft SQL Server",F24)),"Yes","No") -> Yes | I24: Production | J24: Supported | K24: High | L24: DR | M24: IT Operations Team | O24: Infrastructure Team | P24: No | Q24: No | R24: =COUNTIF('3. Databases'!$B$2:$B$192,$A24) -> 0 | S24: {=SUMPRODUCT(('3. Databases'!$B$2:$B$192=$A24)*COUNTIF('Lists (Config)'!$K$4:$K$6,'3. Databases'!$R$2:$R$192))} -> 0 | T24: MSSQL detected | U24: Login failed for user
A25: SRV-021 | B25: BB-VV-SG-002 | C25: 10.196.5.12 | D25: Orlando | E25: Server | F25: Microsoft SQL Server Compact 4.0 SP1 x64 ENU | G25: Express | H25: =IF(ISNUMBER(SEARCH("Microsoft SQL Server",F25)),"Yes","No") -> Yes | I25: DR | K25: Medium | L25: DR | M25: IT Operations Team | N25: Corporate Security | O25: Infrastructure Team | P25: No | Q25: No | R25: =COUNTIF('3. Databases'!$B$2:$B$192,$A25) -> 0 | S25: {=SUMPRODUCT(('3. Databases'!$B$2:$B$192=$A25)*COUNTIF('Lists (Config)'!$K$4:$K$6,'3. Databases'!$R$2:$R$192))} -> 0 | T25: MSSQL detected | U25: The server was not found
A26: SRV-022 | B26: BB-VV-SG-002 | C26: 10.196.5.12 | D26: Orlando | E26: Server | F26: Microsoft SQL Server 2019 (64-bit) | G26: Express | H26: =IF(ISNUMBER(SEARCH("Microsoft SQL Server",F26)),"Yes","No") -> Yes | I26: DR | O26: Infrastructure Team | P26: No | Q26: No | R26: =COUNTIF('3. Databases'!$B$2:$B$192,$A26) -> 0 | S26: {=SUMPRODUCT(('3. Databases'!$B$2:$B$192=$A26)*COUNTIF('Lists (Config)'!$K$4:$K$6,'3. Databases'!$R$2:$R$192))} -> 0 | T26: Duplicate | U26: The server was not found
A27: SRV-023 | B27: BB-VV-WS-002 | C27: 172.29.5.42 | D27: NAP | E27: DMZ | F27: MySQL Server 8.4 | G27: - | H27: =IF(ISNUMBER(SEARCH("Microsoft SQL Server",F27)),"Yes","No") -> No | I27: Production | K27: High | L27: DR | M27: IT Operations Team, Rena Silva | N27: Devs | O27: Infrastructure Team | P27: No | Q27: No | R27: =COUNTIF('3. Databases'!$B$2:$B$192,$A27) -> 0 | S27: {=SUMPRODUCT(('3. Databases'!$B$2:$B$192=$A27)*COUNTIF('Lists (Config)'!$K$4:$K$6,'3. Databases'!$R$2:$R$192))} -> 0 | T27: Non-MSSQL product detected
A28: SRV-019 | B28: BFBASSIST | C28: 10.198.5.104 | D28: NAP | E28: Server | F28: Microsoft SQL Server 2016 (64-bit) | G28: Standard | H28: =IF(ISNUMBER(SEARCH("Microsoft SQL Server",F28)),"Yes","No") -> Yes | I28: Production | J28: End of Support (EOS) | K28: High | L28: DR | M28: IT Operations Team | N28: BSA | O28: Infrastructure Team | P28: No | Q28: No | R28: =COUNTIF('3. Databases'!$B$2:$B$192,$A28) -> 0 | S28: {=SUMPRODUCT(('3. Databases'!$B$2:$B$192=$A28)*COUNTIF('Lists (Config)'!$K$4:$K$6,'3. Databases'!$R$2:$R$192))} -> 0 | T28: MSSQL detected | U28: Login failed for user
A29: SRV-025 | B29: BFBASSIST | C29: 10.198.5.104 | D29: NAP | E29: Server | F29: Microsoft SQL Server 2012 Express LocalDB | G29: Express | H29: =IF(ISNUMBER(SEARCH("Microsoft SQL Server",F29)),"Yes","No") -> Yes | I29: Production | J29: End of Support (EOS) | K29: Medium | L29: DR | M29: IT Operations Team, Yanniel | N29: BSA, Dev | O29: Infrastructure Team | P29: No | Q29: No | R29: =COUNTIF('3. Databases'!$B$2:$B$192,$A29) -> 0 | S29: {=SUMPRODUCT(('3. Databases'!$B$2:$B$192=$A29)*COUNTIF('Lists (Config)'!$K$4:$K$6,'3. Databases'!$R$2:$R$192))} -> 0 | T29: Duplicate | U29: Login failed for user
A30: SRV-024 | B30: BFBASSIST-UAT | C30: 10.198.5.6 | D30: NAP | E30: Server | F30: Microsoft SQL Server 2016 (64-bit) | G30: Standard | H30: =IF(ISNUMBER(SEARCH("Microsoft SQL Server",F30)),"Yes","No") -> Yes | I30: Staging/UAT | K30: Medium | L30: DR | M30: IT Operations Team, Yanniel | N30: BSA, Dev | O30: Infrastructure Team | P30: No | Q30: No | R30: =COUNTIF('3. Databases'!$B$2:$B$192,$A30) -> 0 | S30: {=SUMPRODUCT(('3. Databases'!$B$2:$B$192=$A30)*COUNTIF('Lists (Config)'!$K$4:$K$6,'3. Databases'!$R$2:$R$192))} -> 0 | T30: MSSQL detected | U30: Login failed for user
A31: SRV-028 | B31: BFBASSIST-UAT | C31: 10.198.5.6 | D31: NAP | E31: Server | F31: Microsoft SQL Server 2012 Express LocalDB | G31: Express | H31: =IF(ISNUMBER(SEARCH("Microsoft SQL Server",F31)),"Yes","No") -> Yes | I31: Staging/UAT | K31: Medium | L31: DR | M31: IT Operations Team, Yanniel | N31: BSA, Dev | O31: Infrastructure Team | P31: No | Q31: No | R31: =COUNTIF('3. Databases'!$B$2:$B$192,$A31) -> 0 | S31: {=SUMPRODUCT(('3. Databases'!$B$2:$B$192=$A31)*COUNTIF('Lists (Config)'!$K$4:$K$6,'3. Databases'!$R$2:$R$192))} -> 0 | T31: Duplicate | U31: Login failed for user
A32: SRV-029 | B32: BFBDSNAP | C32: 192.168.105.10 169.254.149.78 | D32: NAP | E32: PCI | F32: Microsoft SQL Server 2019 (64-bit) | G32: Standard | H32: =IF(ISNUMBER(SEARCH("Microsoft SQL Server",F32)),"Yes","No") -> Yes | I32: Production | J32: Supported | K32: High | L32: DR | M32: IT Operations Team, Rena Silva | N32: Devs | O32: Infrastructure Team | P32: No | Q32: No | R32: =COUNTIF('3. Databases'!$B$2:$B$192,$A32) -> 4 | S32: {=SUMPRODUCT(('3. Databases'!$B$2:$B$192=$A32)*COUNTIF('Lists (Config)'!$K$4:$K$6,'3. Databases'!$R$2:$R$192))} -> 0 | T32: MSSQL detected
A33: SRV-044 | B33: BFBDSNAP | C33: 192.168.105.10 169.254.149.78 | D33: NAP | E33: PCI | F33: Microsoft SQL Server 2016 LocalDB | G33: Standard | H33: =IF(ISNUMBER(SEARCH("Microsoft SQL Server",F33)),"Yes","No") -> Yes | I33: Production | J33: Supported | K33: High | L33: DR | M33: IT Operations Team, Rena Silva | N33: Devs | O33: Infrastructure Team | P33: No | Q33: No | R33: =COUNTIF('3. Databases'!$B$2:$B$192,$A33) -> 0 | S33: {=SUMPRODUCT(('3. Databases'!$B$2:$B$192=$A33)*COUNTIF('Lists (Config)'!$K$4:$K$6,'3. Databases'!$R$2:$R$192))} -> 0 | T33: Duplicate | U33: The server was not found
A34: SRV-031 | B34: BFBFEDLINK | C34: 10.198.5.128 | D34: NAP | E34: Server | F34: Microsoft SQL Server 2019 (64-bit) | G34: Standard | H34: =IF(ISNUMBER(SEARCH("Microsoft SQL Server",F34)),"Yes","No") -> Yes | I34: Production | J34: Supported | K34: High | L34: DR | M34: IT Operations Team | N34: Operations Deparment | O34: Infrastructure Team | P34: No | Q34: No | R34: =COUNTIF('3. Databases'!$B$2:$B$192,$A34) -> 0 | S34: {=SUMPRODUCT(('3. Databases'!$B$2:$B$192=$A34)*COUNTIF('Lists (Config)'!$K$4:$K$6,'3. Databases'!$R$2:$R$192))} -> 0 | T34: MSSQL detected | U34: Login failed for user
A35: SRV-055 | B35: BFB-FEDLINK | E35: Server | F35: Microsoft SQL Server 2019 (64-bit) | G35: Standard | H35: =IF(ISNUMBER(SEARCH("Microsoft SQL Server",F35)),"Yes","No") -> Yes | I35: Production | J35: Supported | K35: High | L35: DR | M35: IT Operations Team | N35: Operations Deparment | O35: Linked Server SQL | P35: No | Q35: No | R35: =COUNTIF('3. Databases'!$B$2:$B$192,$A35) -> 1 | S35: {=SUMPRODUCT(('3. Databases'!$B$2:$B$192=$A35)*COUNTIF('Lists (Config)'!$K$4:$K$6,'3. Databases'!$R$2:$R$192))} -> 0 | T35: MSSQL detected
A36: SRV-032 | B36: BFBFEDLINKORL | C36: 10.196.5.24 | D36: Orlando | E36: Server | F36: Microsoft SQL Server 2019 (64-bit) | G36: Standard | H36: =IF(ISNUMBER(SEARCH("Microsoft SQL Server",F36)),"Yes","No") -> Yes | I36: DR | J36: Supported | K36: High | L36: DR | M36: IT Operations Team | N36: Operations Deparment | O36: Infrastructure Team | P36: No | Q36: No | R36: =COUNTIF('3. Databases'!$B$2:$B$192,$A36) -> 0 | S36: {=SUMPRODUCT(('3. Databases'!$B$2:$B$192=$A36)*COUNTIF('Lists (Config)'!$K$4:$K$6,'3. Databases'!$R$2:$R$192))} -> 0 | T36: MSSQL detected | U36: Login failed for user
A37: SRV-033 | B37: BFBJXSERVER1 | C37: 10.198.5.170 10.198.5.221 | D37: NAP | E37: Server | F37: Microsoft SQL Server Compact 3.5 SP2 ENU | G37: - | H37: =IF(ISNUMBER(SEARCH("Microsoft SQL Server",F37)),"Yes","No") -> Yes | I37: Production | J37: End of Support (EOS) | K37: Medium | L37: DR | M37: IT Operations Team | N37: Operations Deparment | O37: Infrastructure Team | P37: No | Q37: No | R37: =COUNTIF('3. Databases'!$B$2:$B$192,$A37) -> 0 | S37: {=SUMPRODUCT(('3. Databases'!$B$2:$B$192=$A37)*COUNTIF('Lists (Config)'!$K$4:$K$6,'3. Databases'!$R$2:$R$192))} -> 0 | T37: No SQL Installed. | U37: The server was not found
A38: SRV-034 | B38: BFBJXSERVER2 | C38: 10.198.5.171 10.198.5.222 | D38: NAP | E38: Server | F38: Microsoft SQL Server Compact 3.5 SP2 ENU | G38: - | H38: =IF(ISNUMBER(SEARCH("Microsoft SQL Server",F38)),"Yes","No") -> Yes | I38: Production | J38: End of Support (EOS) | K38: Medium | L38: DR | M38: IT Operations Team | N38: Operations Deparment | O38: Infrastructure Team | P38: No | Q38: No | R38: =COUNTIF('3. Databases'!$B$2:$B$192,$A38) -> 0 | S38: {=SUMPRODUCT(('3. Databases'!$B$2:$B$192=$A38)*COUNTIF('Lists (Config)'!$K$4:$K$6,'3. Databases'!$R$2:$R$192))} -> 0 | T38: No SQL Installed. | U38: The server was not found
A39: SRV-035 | B39: BFBJXSERVERDB | C39: 10.198.5.108 | D39: NAP | E39: Server | F39: Microsoft SQL Server 2019 (64-bit) | G39: Standard | H39: =IF(ISNUMBER(SEARCH("Microsoft SQL Server",F39)),"Yes","No") -> Yes | I39: Production | J39: Supported | K39: High | L39: DR | M39: IT Operations Team | N39: Operations Deparment | O39: Infrastructure Team | P39: No | Q39: No | R39: =COUNTIF('3. Databases'!$B$2:$B$192,$A39) -> 0 | S39: {=SUMPRODUCT(('3. Databases'!$B$2:$B$192=$A39)*COUNTIF('Lists (Config)'!$K$4:$K$6,'3. Databases'!$R$2:$R$192))} -> 0 | T39: MSSQL detected | U39: The server was not found
A40: SRV-036 | B40: BFBJXWORKFLOWDB | C40: 10.198.5.37 | D40: NAP | E40: Server | F40: Microsoft SQL Server 2019 (64-bit) | G40: Standard | H40: =IF(ISNUMBER(SEARCH("Microsoft SQL Server",F40)),"Yes","No") -> Yes | I40: Production | J40: Supported | K40: High | L40: DR | M40: IT Operations Team | N40: Operations Deparment | O40: Infrastructure Team | P40: Yes | Q40: No | R40: =COUNTIF('3. Databases'!$B$2:$B$192,$A40) -> 7 | S40: {=SUMPRODUCT(('3. Databases'!$B$2:$B$192=$A40)*COUNTIF('Lists (Config)'!$K$4:$K$6,'3. Databases'!$R$2:$R$192))} -> 0 | T40: MSSQL detected
A41: SRV-037 | B41: BFBKAS | C41: 10.198.5.94 | D41: NAP | E41: Server | F41: Microsoft SQL Server 2019 (64-bit) | G41: Express | H41: =IF(ISNUMBER(SEARCH("Microsoft SQL Server",F41)),"Yes","No") -> Yes | I41: Production | J41: Supported | K41: Medium | L41: DR | M41: IT Operations Team | O41: Infrastructure Team | P41: No | Q41: No | R41: =COUNTIF('3. Databases'!$B$2:$B$192,$A41) -> 0 | S41: {=SUMPRODUCT(('3. Databases'!$B$2:$B$192=$A41)*COUNTIF('Lists (Config)'!$K$4:$K$6,'3. Databases'!$R$2:$R$192))} -> 0 | T41: SQL installed; no business databases found. | U41: The server was not found
A42: SRV-026 | B42: BFBNAPDB | C42: 10.198.5.205 | D42: NAP | E42: Server | F42: Microsoft SQL Server 2016 (64-bit) | G42: Standard | H42: =IF(ISNUMBER(SEARCH("Microsoft SQL Server",F42)),"Yes","No") -> Yes | I42: Production | K42: High | L42: DR | M42: IT Operations Team, Rena Silva | N42: Devs | O42: Infrastructure Team | P42: Yes | Q42: No | R42: =COUNTIF('3. Databases'!$B$2:$B$192,$A42) -> 36 | S42: {=SUMPRODUCT(('3. Databases'!$B$2:$B$192=$A42)*COUNTIF('Lists (Config)'!$K$4:$K$6,'3. Databases'!$R$2:$R$192))} -> 0 | T42: MSSQL detected
A43: SRV-040 | B43: BFBNAPDB | C43: 10.198.5.205 | D43: NAP | E43: Server | F43: MySQL Server 8.0 | G43: - | H43: =IF(ISNUMBER(SEARCH("Microsoft SQL Server",F43)),"Yes","No") -> No | I43: Production | J43: Supported | K43: High | L43: DR | M43: IT Operations Team, Rena Silva | N43: Devs | O43: Infrastructure Team | P43: No | Q43: No | R43: =COUNTIF('3. Databases'!$B$2:$B$192,$A43) -> 0 | S43: {=SUMPRODUCT(('3. Databases'!$B$2:$B$192=$A43)*COUNTIF('Lists (Config)'!$K$4:$K$6,'3. Databases'!$R$2:$R$192))} -> 0 | T43: MSSQL detected
A44: SRV-046 | B44: BFBNAPDB | C44: 10.198.5.205 | D44: NAP | E44: Server | F44: Microsoft SQL Server 2016 LocalDB | G44: Standard | H44: =IF(ISNUMBER(SEARCH("Microsoft SQL Server",F44)),"Yes","No") -> Yes | I44: Production | K44: High | L44: DR | M44: IT Operations Team, Rena Silva | N44: Devs | O44: Infrastructure Team | P44: No | Q44: No | R44: =COUNTIF('3. Databases'!$B$2:$B$192,$A44) -> 0 | S44: {=SUMPRODUCT(('3. Databases'!$B$2:$B$192=$A44)*COUNTIF('Lists (Config)'!$K$4:$K$6,'3. Databases'!$R$2:$R$192))} -> 0 | T44: MSSQL detected | U44: Same server as SRV-026
A45: SRV-027 | B45: BFBNAPLC | C45: 10.198.5.95 | D45: NAP | E45: Server | F45: Microsoft SQL Server 2016 (64-bit) | G45: Standard | H45: =IF(ISNUMBER(SEARCH("Microsoft SQL Server",F45)),"Yes","No") -> Yes | I45: Production | K45: High | L45: DR | M45: IT Operations Team | N45: Operations Deparment | BSA | O45: Infrastructure Team | P45: No | Q45: No | R45: =COUNTIF('3. Databases'!$B$2:$B$192,$A45) -> 0 | S45: {=SUMPRODUCT(('3. Databases'!$B$2:$B$192=$A45)*COUNTIF('Lists (Config)'!$K$4:$K$6,'3. Databases'!$R$2:$R$192))} -> 0 | T45: MSSQL detected | U45: Login failed for user
A46: SRV-030 | B46: BFBOFACAPI | C46: 172.29.5.26 | D46: NAP | E46: DMZ | F46: Microsoft SQL Server 2016 (64-bit) | G46: Standard | H46: =IF(ISNUMBER(SEARCH("Microsoft SQL Server",F46)),"Yes","No") -> Yes | I46: Production | J46: Supported | K46: High | L46: DR | M46: IT Operations Team | O46: Infrastructure Team | P46: No | Q46: No | R46: =COUNTIF('3. Databases'!$B$2:$B$192,$A46) -> 0 | S46: {=SUMPRODUCT(('3. Databases'!$B$2:$B$192=$A46)*COUNTIF('Lists (Config)'!$K$4:$K$6,'3. Databases'!$R$2:$R$192))} -> 0 | T46: Non-MSSQL product detected | U46: The server was not found
A47: SRV-043 | B47: BFBOFACORL | C47: 10.196.5.28 | D47: Orlando | E47: Server | F47: Microsoft SQL Server 2019 (64-bit) | G47: Standard | H47: =IF(ISNUMBER(SEARCH("Microsoft SQL Server",F47)),"Yes","No") -> Yes | I47: DR | J47: Supported | K47: High | L47: DR | M47: IT Operations Team | N47: Operations Deparment | O47: Infrastructure Team | P47: No | Q47: No | R47: =COUNTIF('3. Databases'!$B$2:$B$192,$A47) -> 0 | S47: {=SUMPRODUCT(('3. Databases'!$B$2:$B$192=$A47)*COUNTIF('Lists (Config)'!$K$4:$K$6,'3. Databases'!$R$2:$R$192))} -> 0 | T47: MSSQL detected | U47: Login failed for user
A48: SRV-038 | B48: BFBORLDB | C48: 10.196.5.205 | D48: Orlando | E48: Server | F48: Microsoft SQL Server 2016 (64-bit) | G48: Standard | H48: =IF(ISNUMBER(SEARCH("Microsoft SQL Server",F48)),"Yes","No") -> Yes | I48: DR | K48: High | L48: DR | M48: IT Operations Team | N48: Devs | O48: Infrastructure Team | P48: No | Q48: No | R48: =COUNTIF('3. Databases'!$B$2:$B$192,$A48) -> 0 | S48: {=SUMPRODUCT(('3. Databases'!$B$2:$B$192=$A48)*COUNTIF('Lists (Config)'!$K$4:$K$6,'3. Databases'!$R$2:$R$192))} -> 0 | T48: MSSQL detected | U48: Login failed for user
A49: SRV-045 | B49: BFBORLDB | C49: 10.196.5.205 | D49: Orlando | E49: Server | F49: MySQL Server 8.0 | G49: - | H49: =IF(ISNUMBER(SEARCH("Microsoft SQL Server",F49)),"Yes","No") -> No | I49: DR | K49: High | L49: DR | M49: IT Operations Team | O49: Infrastructure Team | P49: No | Q49: No | R49: =COUNTIF('3. Databases'!$B$2:$B$192,$A49) -> 0 | S49: {=SUMPRODUCT(('3. Databases'!$B$2:$B$192=$A49)*COUNTIF('Lists (Config)'!$K$4:$K$6,'3. Databases'!$R$2:$R$192))} -> 0 | T49: MSSQL detected
A50: SRV-039 | B50: BFBORLLC | C50: 10.196.5.210 | D50: Orlando | E50: Server | F50: Microsoft SQL Server 2016 (64-bit) | G50: Standard | H50: =IF(ISNUMBER(SEARCH("Microsoft SQL Server",F50)),"Yes","No") -> Yes | I50: DR | K50: Medium | L50: DR | M50: IT Operations Team | N50: Finance | O50: Infrastructure Team | P50: No | Q50: No | R50: =COUNTIF('3. Databases'!$B$2:$B$192,$A50) -> 0 | S50: {=SUMPRODUCT(('3. Databases'!$B$2:$B$192=$A50)*COUNTIF('Lists (Config)'!$K$4:$K$6,'3. Databases'!$R$2:$R$192))} -> 0 | T50: MSSQL detected | U50: Login failed for user
A51: SRV-041 | B51: BFBREPORTS | C51: 10.198.5.189 | D51: NAP | E51: Server | F51: Microsoft SQL Server 2016 (64-bit) | G51: Standard | H51: =IF(ISNUMBER(SEARCH("Microsoft SQL Server",F51)),"Yes","No") -> Yes | I51: Production | K51: High | L51: DR | M51: IT Operations Team, Rena Silva | N51: Devs | O51: Infrastructure Team | P51: No | Q51: No | R51: =COUNTIF('3. Databases'!$B$2:$B$192,$A51) -> 0 | S51: {=SUMPRODUCT(('3. Databases'!$B$2:$B$192=$A51)*COUNTIF('Lists (Config)'!$K$4:$K$6,'3. Databases'!$R$2:$R$192))} -> 0 | T51: MSSQL detected | U51: Login failed for user
A52: SRV-048 | B52: BFBSYNDB | C52: 10.198.5.225 | D52: NAP | E52: Server | F52: Microsoft SQL Server 2019 (64-bit) | G52: Standard | H52: =IF(ISNUMBER(SEARCH("Microsoft SQL Server",F52)),"Yes","No") -> Yes | I52: Production | J52: Supported | K52: High | L52: DR | M52: IT Operations Team | N52: Operations Deparment | O52: Infrastructure Team | P52: No | Q52: No | R52: =COUNTIF('3. Databases'!$B$2:$B$192,$A52) -> 0 | S52: {=SUMPRODUCT(('3. Databases'!$B$2:$B$192=$A52)*COUNTIF('Lists (Config)'!$K$4:$K$6,'3. Databases'!$R$2:$R$192))} -> 0 | T52: MSSQL detected | U52: Login failed for user
A53: SRV-049 | B53: BFBWEBDEV | C53: 10.196.5.92 10.196.5.90 10.196.5.91 | D53: Orlando | E53: Server | F53: Microsoft SQL Server 2019 (64-bit) | G53: Express | H53: =IF(ISNUMBER(SEARCH("Microsoft SQL Server",F53)),"Yes","No") -> Yes | I53: Development | J53: Supported | K53: Medium | L53: DR | M53: IT Operations Team, Rena Silva | N53: Devs | O53: Infrastructure Team | P53: No | Q53: No | R53: =COUNTIF('3. Databases'!$B$2:$B$192,$A53) -> 0 | S53: {=SUMPRODUCT(('3. Databases'!$B$2:$B$192=$A53)*COUNTIF('Lists (Config)'!$K$4:$K$6,'3. Databases'!$R$2:$R$192))} -> 0 | T53: Non-MSSQL product detected | U53: The server was not found
A54: SRV-050 | B54: BFBWEBDEV | C54: 10.196.5.92 10.196.5.90 10.196.5.91 | D54: Orlando | E54: Server | F54: MySQL Server 5.7 | G54: - | H54: =IF(ISNUMBER(SEARCH("Microsoft SQL Server",F54)),"Yes","No") -> No | I54: Duplicated | O54: Infrastructure Team | P54: No | Q54: No | R54: =COUNTIF('3. Databases'!$B$2:$B$192,$A54) -> 0 | S54: {=SUMPRODUCT(('3. Databases'!$B$2:$B$192=$A54)*COUNTIF('Lists (Config)'!$K$4:$K$6,'3. Databases'!$R$2:$R$192))} -> 0 | T54: Duplicate
A55: SRV-051 | B55: EBANCWEB1 | C55: 172.29.5.6 172.29.5.4 172.29.5.2 172.29.5.3 172.29.5.5 172.29.5.8 | D55: NAP | E55: DMZ | F55: MySQL Server 5.7 | G55: - | H55: =IF(ISNUMBER(SEARCH("Microsoft SQL Server",F55)),"Yes","No") -> No | I55: Production | K55: High | L55: DR | M55: IT Operations Team, Rena Silva | N55: IT Operations Team, Devs | O55: Infrastructure Team | P55: No | Q55: No | R55: =COUNTIF('3. Databases'!$B$2:$B$192,$A55) -> 0 | S55: {=SUMPRODUCT(('3. Databases'!$B$2:$B$192=$A55)*COUNTIF('Lists (Config)'!$K$4:$K$6,'3. Databases'!$R$2:$R$192))} -> 0 | T55: Non-MSSQL product detected
A56: SRV-057 | B56: sqlserver-7db9877b68-6h74t | E56: Server | F56: Microsoft SQL Server 2022 (64-bit) | G56: Unknown | H56: =IF(ISNUMBER(SEARCH("Microsoft SQL Server",F56)),"Yes","No") -> Yes | I56: Development | M56: Renan Silva | N56: Devs | O56: Other Team | P56: Yes | Q56: Yes | R56: =COUNTIF('3. Databases'!$B$2:$B$192,$A56) -> 10 | S56: {=SUMPRODUCT(('3. Databases'!$B$2:$B$192=$A56)*COUNTIF('Lists (Config)'!$K$4:$K$6,'3. Databases'!$R$2:$R$192))} -> 0 | T56: Devs NiFi
A57: SRV-047 | B57: UATSYNDB | C57: 10.198.5.161 | D57: NAP | E57: Server | F57: Microsoft SQL Server 2016 LocalDB | G57: Standard | H57: =IF(ISNUMBER(SEARCH("Microsoft SQL Server",F57)),"Yes","No") -> Yes | I57: Staging/UAT | K57: Medium | L57: DR | M57: IT Operations Team, Rena Silva | N57: IT Operations Team, Devs | O57: Infrastructure Team | P57: No | Q57: No | R57: =COUNTIF('3. Databases'!$B$2:$B$192,$A57) -> 0 | S57: {=SUMPRODUCT(('3. Databases'!$B$2:$B$192=$A57)*COUNTIF('Lists (Config)'!$K$4:$K$6,'3. Databases'!$R$2:$R$192))} -> 0 | T57: MSSQL detected | U57: Login failed for user
A58: SRV-052 | B58: UATSYNDB | C58: 10.198.5.161 | D58: NAP | E58: Server | F58: Microsoft SQL Server 2019 (64-bit) | G58: Standard | H58: =IF(ISNUMBER(SEARCH("Microsoft SQL Server",F58)),"Yes","No") -> Yes | I58: Staging/UAT | K58: Medium | L58: DR | M58: IT Operations Team, Rena Silva | N58: IT Operations Team, Devs | O58: Infrastructure Team | P58: No | Q58: No | R58: =COUNTIF('3. Databases'!$B$2:$B$192,$A58) -> 35 | S58: {=SUMPRODUCT(('3. Databases'!$B$2:$B$192=$A58)*COUNTIF('Lists (Config)'!$K$4:$K$6,'3. Databases'!$R$2:$R$192))} -> 0 | T58: Duplicate
A59: SRV-058 | B59: sqlserver-6d45bcd4bf-vz9k2 | E59: Server | F59: Microsoft SQL Server 2022 (64-bit) | G59: Unknown | H59: =IF(ISNUMBER(SEARCH("Microsoft SQL Server",F59)),"Yes","No") -> Yes | I59: Development | M59: Renan Silva | N59: Devs | O59: Other Team | P59: Yes | Q59: Yes | R59: =COUNTIF('3. Databases'!$B$2:$B$192,$A59) -> 5 | S59: {=SUMPRODUCT(('3. Databases'!$B$2:$B$192=$A59)*COUNTIF('Lists (Config)'!$K$4:$K$6,'3. Databases'!$R$2:$R$192))} -> 0 | T59: Devs NiFi

Sheet 3. Databases
A1: DatabaseID | B1: ServerID (link to Tab 2) | C1: Database Name | D1: SQL Version (reported) | E1: State | F1: Size (MB) | G1: Last Backup | H1: mdf | I1: ldf | J1: Environment | K1: Criticality | L1: Application / Functional Owner | M1: Use / Purpose | N1: Sources Owner | O1: Sources | P1: Dependency Owner | Q1: Dependecy | R1: Migration Status | S1: Recommendation | T1: Discovery Source | U1: Notes
A2: DB-085 | B2: SRV-002 | C2: BAC_BRAD | D2: SQL Server 2016 | E2: ONLINE | F2: 1665.88 | G2: 7/14/2026 4:00 | H2: C:\Program Files\Microsoft SQL Server\MSSQL13.MSSQLSERVER\MSSQL\DATA\BAC_BRAD.mdf | I2: C:\Program Files\Microsoft SQL Server\MSSQL13.MSSQLSERVER\MSSQL\DATA\BAC_BRAD_log.ldf | J2: Pending validation | R2: Pending analysis | T2: Linked Server SQL
A3: DB-086 | B3: SRV-002 | C3: BAC_BRAD_frozzen | D3: SQL Server 2016 | E3: ONLINE | F3: 976 | G3: 7/14/2026 4:00 | H3: C:\Program Files\Microsoft SQL Server\MSSQL13.MSSQLSERVER\MSSQL\DATA\BAC_BRAD_frozzen.mdf | I3: C:\Program Files\Microsoft SQL Server\MSSQL13.MSSQLSERVER\MSSQL\DATA\BAC_BRAD_frozzen_log.ldf | J3: Pending validation | R3: Pending analysis | T3: Linked Server SQL
A4: DB-087 | B4: SRV-002 | C4: BAC_BRAD_preprod_1 | D4: SQL Server 2016 | E4: ONLINE | F4: 2068 | G4: 7/14/2026 4:00 | H4: C:\Program Files\Microsoft SQL Server\MSSQL13.MSSQLSERVER\MSSQL\DATA\BAC_BRAD_preprod_1 | I4: C:\Program Files\Microsoft SQL Server\MSSQL13.MSSQLSERVER\MSSQL\DATA\BAC_BRAD_preprod_1_log | J4: Pending validation | R4: Pending analysis | T4: Linked Server SQL
A5: DB-088 | B5: SRV-002 | C5: BAC_BRAD_preprod_GO | D5: SQL Server 2016 | E5: ONLINE | F5: 2068 | G5: 7/14/2026 4:00 | H5: C:\Program Files\Microsoft SQL Server\MSSQL13.MSSQLSERVER\MSSQL\DATA\BAC_BRAD_preprod_GO | I5: C:\Program Files\Microsoft SQL Server\MSSQL13.MSSQLSERVER\MSSQL\DATA\BAC_BRAD_preprod_GO_log | J5: Pending validation | R5: Pending analysis | T5: Linked Server SQL
A6: DB-089 | B6: SRV-002 | C6: BAC_BRAD_preprod_HML | D6: SQL Server 2016 | E6: ONLINE | F6: 2576 | G6: 7/14/2026 4:00 | H6: C:\Program Files\Microsoft SQL Server\MSSQL13.MSSQLSERVER\MSSQL\DATA\BAC_BRAD_preprod_HML.mdf | I6: C:\Program Files\Microsoft SQL Server\MSSQL13.MSSQLSERVER\MSSQL\DATA\BAC_BRAD_preprod_HML_log.ldf | J6: Pending validation | R6: Pending analysis | T6: Linked Server SQL
A7: DB-090 | B7: SRV-002 | C7: BAC_BRAD_preprod_HML2 | D7: SQL Server 2016 | E7: ONLINE | F7: 3604 | G7: 7/14/2026 4:00 | H7: C:\Program Files\Microsoft SQL Server\MSSQL13.MSSQLSERVER\MSSQL\DATA\BAC_BRAD_preprod_HML2 | I7: C:\Program Files\Microsoft SQL Server\MSSQL13.MSSQLSERVER\MSSQL\DATA\BAC_BRAD_preprod_HML2_log | J7: Pending validation | R7: Pending analysis | T7: Linked Server SQL
A8: DB-091 | B8: SRV-002 | C8: BAC_BRAD_prod_TMP | D8: SQL Server 2016 | E8: ONLINE | F8: 1684 | G8: 7/14/2026 4:00 | H8: C:\Program Files\Microsoft SQL Server\MSSQL13.MSSQLSERVER\MSSQL\DATA\BAC_BRAD_prod | I8: C:\Program Files\Microsoft SQL Server\MSSQL13.MSSQLSERVER\MSSQL\DATA\BAC_BRAD_prod_log | J8: Pending validation | R8: Pending analysis | T8: Linked Server SQL
A9: DB-092 | B9: SRV-002 | C9: BAC_BRAD_stage_test4 | D9: SQL Server 2016 | E9: ONLINE | F9: 208 | G9: 7/14/2026 4:00 | H9: C:\Program Files\Microsoft SQL Server\MSSQL13.MSSQLSERVER\MSSQL\DATA\BAC_BRAD_stage_test4.mdf | I9: C:\Program Files\Microsoft SQL Server\MSSQL13.MSSQLSERVER\MSSQL\DATA\BAC_BRAD_stage_test4_log.ldf | J9: Pending validation | R9: Pending analysis | T9: Linked Server SQL
A10: DB-093 | B10: SRV-002 | C10: BAC_BRAD_stage_test5 | D10: SQL Server 2016 | E10: ONLINE | F10: 400 | G10: 7/14/2026 4:00 | H10: C:\Program Files\Microsoft SQL Server\MSSQL13.MSSQLSERVER\MSSQL\DATA\BAC_BRAD_stage_test5.mdf | I10: C:\Program Files\Microsoft SQL Server\MSSQL13.MSSQLSERVER\MSSQL\DATA\BAC_BRAD_stage_test5_log.ldf | J10: Pending validation | R10: Pending analysis | T10: Linked Server SQL
A11: DB-094 | B11: SRV-002 | C11: BAC_BRAD_stage2 | D11: SQL Server 2016 | E11: ONLINE | F11: 592 | G11: 7/14/2026 4:00 | H11: C:\Program Files\Microsoft SQL Server\MSSQL13.MSSQLSERVER\MSSQL\DATA\BAC_BRAD_stage2.mdf | I11: C:\Program Files\Microsoft SQL Server\MSSQL13.MSSQLSERVER\MSSQL\DATA\BAC_BRAD_stage2_log.ldf | J11: Pending validation | R11: Pending analysis | T11: Linked Server SQL
A12: DB-095 | B12: SRV-002 | C12: BAC_BRAD_test | D12: SQL Server 2016 | E12: ONLINE | F12: 592 | G12: 7/14/2026 4:00 | H12: C:\Program Files\Microsoft SQL Server\MSSQL13.MSSQLSERVER\MSSQL\DATA\BAC_BRAD_test.mdf | I12: C:\Program Files\Microsoft SQL Server\MSSQL13.MSSQLSERVER\MSSQL\DATA\BAC_BRAD_test_log.ldf | J12: Pending validation | R12: Pending analysis | T12: Linked Server SQL
A13: DB-096 | B13: SRV-002 | C13: BAC_BRAD_test2 | D13: SQL Server 2016 | E13: ONLINE | F13: 592 | G13: 7/14/2026 4:00 | H13: C:\Program Files\Microsoft SQL Server\MSSQL13.MSSQLSERVER\MSSQL\DATA\BAC_BRAD_test2.mdf | I13: C:\Program Files\Microsoft SQL Server\MSSQL13.MSSQLSERVER\MSSQL\DATA\BAC_BRAD_test2_log.ldf | J13: Pending validation | R13: Pending analysis | T13: Linked Server SQL
... A41: DB-124 | B41: SRV-002 | C41: TRANSACT | D41: SQL Server 2016 | E41: ONLINE | F41: 426.56 | G41: 7/14/2026 4:00 | H41: C:\Program Files\Microsoft SQL Server\MSSQL13.MSSQLSERVER\MSSQL\DATA\TRANSACT_STAGE.mdf | I41: C:\Program Files\Microsoft SQL Server\MSSQL13.MSSQLSERVER\MSSQL\DATA\TRANSACT_STAGE_log.ldf | J41: Pending validation | R41: Pending analysis | T41: Linked Server SQL
A42: DB-040 | B42: SRV-006 | C42: QSLAR_8546_2016 | D42: SQL Server 2017 | E42: ONLINE | J42: Pending validation | R42: Pending analysis | T42: SQL Server Access | U42: Discovered from SSMS; compatibility level, size, backup and drive pending SQL query.
A43: DB-041 | B43: SRV-006 | C43: QSLAR_8546_2017 | D43: SQL Server 2017 | E43: ONLINE | J43: Pending validation | R43: Pending analysis | T43: SQL Server Access | U43: Discovered from SSMS; compatibility level, size, backup and drive pending SQL query.
A44: DB-042 | B44: SRV-006 | C44: QSLAR_8546_2018 | D44: SQL Server 2017 | E44: ONLINE | J44: Pending validation | R44: Pending analysis | T44: SQL Server Access | U44: Discovered from SSMS; compatibility level, size, backup and drive pending SQL query.
A45: DB-043 | B45: SRV-006 | C45: QSLAR_8546_2019 | D45: SQL Server 2017 | E45: ONLINE | J45: Pending validation | R45: Pending analysis | T45: SQL Server Access | U45: Discovered from SSMS; compatibility level, size, backup and drive pending SQL query.
A46: DB-044 | B46: SRV-006 | C46: QSLAR_8546_2020 | D46: SQL Server 2017 | E46: ONLINE | J46: Pending validation | R46: Pending analysis | T46: SQL Server Access | U46: Discovered from SSMS; compatibility level, size, backup and drive pending SQL query.
A47: DB-045 | B47: SRV-006 | C47: QSLAR_8546_2021 | D47: SQL Server 2017 | E47: ONLINE | J47: Pending validation | R47: Pending analysis | T47: SQL Server Access | U47: Discovered from SSMS; compatibility level, size, backup and drive pending SQL query.
A48: DB-046 | B48: SRV-006 | C48: QSLAR_8546_2022 | D48: SQL Server 2017 | E48: ONLINE | J48: Pending validation | R48: Pending analysis | T48: SQL Server Access | U48: Discovered from SSMS; compatibility level, size, backup and drive pending SQL query.
A49: DB-047 | B49: SRV-006 | C49: QSLAR_8546_2023 | D49: SQL Server 2017 | E49: ONLINE | J49: Pending validation | R49: Pending analysis | T49: SQL Server Access | U49: Discovered from SSMS; compatibility level, size, backup and drive pending SQL query.
A50: DB-048 | B50: SRV-006 | C50: QSLAR_8546_2024 | D50: SQL Server 2017 | E50: ONLINE | J50: Pending validation | R50: Pending analysis | T50: SQL Server Access | U50: Discovered from SSMS; compatibility level, size, backup and drive pending SQL query.
A51: DB-049 | B51: SRV-006 | C51: QSLAR_8546_2025 | D51: SQL Server 2017 | E51: ONLINE | J51: Pending validation | R51: Pending analysis | T51: SQL Server Access | U51: Discovered from SSMS; compatibility level, size, backup and drive pending SQL query.
A52: DB-050 | B52: SRV-006 | C52: QSLAR_9999_2016 | D52: SQL Server 2017 | E52: ONLINE | J52: Pending validation | R52: Pending analysis | T52: SQL Server Access | U52: Discovered from SSMS; compatibility level, size, backup and drive pending SQL query.
A53: DB-051 | B53: SRV-006 | C53: QSLAR_9999_2017 | D53: SQL Server 2017 | E53: ONLINE | J53: Pending validation | R53: Pending analysis | T53: SQL Server Access | U53: Discovered from SSMS; compatibility level, size, backup and drive pending SQL query.
... A64: DB-062 | B64: SRV-006 | C64: QSMaster_9999 | D64: SQL Server 2017 | E64: ONLINE | J64: Pending validation | R64: Pending analysis | T64: SQL Server Access | U64: Discovered from SSMS; compatibility level, size, backup and drive pending SQL query.
A65: DB-063 | B65: SRV-015 | C65: BB_DATA | D65: SQL Server 2019 | E65: ONLINE | F65: 459280 | G65: 7/14/2026 3:42 | H65: D:\Program Files\Microsoft SQL Server\MSSQL15.MSSQLSERVER\MSSQL\DATA\BB_DATA.mdf | I65: E:\Program Files\Microsoft SQL Server\MSSQL15.MSSQLSERVER\MSSQL\Data\BB_DATA_log.ldf | J65: Pending validation | M65: Aproximadamente 90% de ciertos Management Reports y Dashboards, todavia apuntan a BB_DATA y no han sido migrados a DW. | R65: Pending analysis | T65: SQL Server Access | U65: Meeting del 2026-07-22 con Eric y Yanniel: - Este servidor/base (BB-VV-BD-001) esta en proceso de decommission o reemplazo. Antes de apagarlo, todo debe ser migrado hacia DW.
A66: DB-064 | B66: SRV-015 | C66: BB_PROCESS_DATA | D66: SQL Server 2019 | E66: ONLINE | F66: 318544 | G66: 7/14/2026 3:31 | H66: D:\Program Files\Microsoft SQL Server\MSSQL15.MSSQLSERVER\MSSQL\DATA\BB_PROCESS.mdf | I66: E:\Program Files\Microsoft SQL Server\MSSQL15.MSSQLSERVER\MSSQL\Data\BB_PROCESS_log.ldf | J66: Pending validation | R66: Pending analysis | T66: SQL Server Access | U66: Discovered from SSMS; compatibility level, size, backup and drive pending SQL query.
A67: DB-065 | B67: SRV-015 | C67: DWConfiguration | D67: SQL Server 2019 | E67: ONLINE | J67: Pending validation | R67: Pending analysis | T67: SQL Server Access | U67: Discovered from SSMS; compatibility level, size, backup and drive pending SQL query.
A68: DB-066 | B68: SRV-015 | C68: DWDiagnostics | D68: SQL Server 2019 | E68: ONLINE | J68: Pending validation | R68: Pending analysis | T68: SQL Server Access | U68: Discovered from SSMS; compatibility level, size, backup and drive pending SQL query.
A69: DB-067 | B69: SRV-015 | C69: DWQueue | D69: SQL Server 2019 | E69: ONLINE | J69: Pending validation | R69: Pending analysis | T69: SQL Server Access | U69: Discovered from SSMS; compatibility level, size, backup and drive pending SQL query.
A70: DB-001 | B70: SRV-026 | C70: AXIOM | D70: SQL Server 2016 | E70: ONLINE | F70: 336 | G70: 7/14/2026 3:51 | H70: I:\SQL Databases\AXIOM.mdf | I70: F:\SQL Logs\AXIOM_log.ldf | J70: Production | K70: Low | L70: Yanniel / Eric / Grass | M70: Generate Files csv | N70: AXIOM | O70: SSIS - Core Bank DB2 | P70: Reafel Praga - Finnance System | Q70: Flat File | R70: Pending analysis | S70: Pending validation | T70: Technical Documentation | U70: Consolidated: sum of the 2 source rows (data + log files) for this database in the original export.
A71: DB-002 | B71: SRV-026 | C71: B2BTXWEBAPP | D71: SQL Server 2008/R2 | E71: ONLINE | F71: 12.56 | G71: 7/14/2026 3:51 | H71: I:\SQL Databases\B2BTXWEBAPP.mdf | I71: F:\SQL Logs\B2BTXWEBAPP_log.ldf | J71: Pending validation | K71: Unknown | R71: Pending analysis | S71: Decommission | T71: Technical Documentation | U71: Deprecated
A72: DB-003 | B72: SRV-026 | C72: BAC_BRAD_preprod | D72: SQL Server 2016 | E72: ONLINE | F72: 16 | G72: 7/14/2026 3:51 | H72: I:\SQL Databases\BAC_BRAD_preprod.mdf | I72: F:\SQL Logs\BAC_BRAD_preprod_log.ldf | J72: Development | K72: Low | L72: Andres Paulino | M72: OnBoarding sys | R72: Pending analysis | S72: Keep | T72: Technical Documentation | U72: Consolidated: sum of the 2 source rows (data + log files) for this database in the original export.
A73: DB-004 | B73: SRV-026 | C73: BAC_BRAD_prod | D73: SQL Server 2016 | E73: ONLINE | F73: 7892 | G73: 7/14/2026 3:51 | H73: I:\SQL Databases\BAC_BRAD_prod.mdf | I73: F:\SQL Logs\BAC_BRAD_prod_log.ldf | J73: Production | K73: Critical | L73: Andres Paulino | M73: OnBoarding sys (COS) | N73: Bradesco Bank Engineering | O73: Web App - Users ; API ; Documment Sign | P73: Bradesco Bank Engineering | Q73: Web App - API | R73: Pending analysis | S73: Keep | T73: Technical Documentation | U73: Consolidated: sum of the 2 source rows (data + log files) for this database in the original export.
A74: DB-005 | B74: SRV-026 | C74: BAC_BRAD_stage | D74: SQL Server 2008/R2 | E74: ONLINE | F74: 610.38 | G74: 7/14/2026 3:51 | H74: I:\SQL Databases\BAC_BRAD_stage.mdf | I74: F:\SQL Logs\BAC_BRAD_stage_log.ldf | J74: Staging/UAT | K74: Unknown | L74: Andres Paulino | M74: OnBoarding sys | R74: Pending analysis | S74: Decommission | T74: Technical Documentation | U74: Consolidated: sum of the 2 source rows (data + log files) for this database in the original export.
A75: DB-006 | B75: SRV-026 | C75: BAC_DI | D75: SQL Server 2008/R2 | E75: ONLINE | F75: 43146.56 | G75: 7/14/2026 3:51 | H75: I:\SQL Databases\BAC_DI.mdf | I75: F:\SQL Logs\BAC_DI_log.ldf | J75: Production | K75: Low | L75: Yanniel / Eric / Grass | M75: Origen de los datos: Core System Reports (SSRS) | N75: Yanniel | O75: Core System | P75: Yanniel | Q75: Reports | R75: Pending analysis | S75: Pending validation | T75: Technical Documentation | U75: Meeting del 2026-07-22 con Eric y Yanniel: - Need to verify maintence reports - Yanniel indico que todavia carga datos mensualmente, aunque no esta claro que tanto consumo real existe hoy - La conclusion fue que puede seguir en uso, no parece critica y requiere validacion antes de decidir decommission.
A76: DB-007 | B76: SRV-026 | C76: BAC_DI_STAGE | D76: SQL Server 2008/R2 | E76: ONLINE | F76: 4983.56 | G76: 7/14/2026 3:51 | H76: I:\SQL Databases\BAC_DI_STAGE.mdf | I76: F:\SQL Logs\BAC_DI_STAGE_log.ldf | J76: Staging/UAT | K76: Low | L76: Yanniel / Eric / Grass | M76: N/A | N76: Yanniel | O76: N/A | P76: N/A | Q76: N/A | R76: Retire | S76: Decommission | T76: Technical Documentation | U76: Meeting del 2026-07-22 con Eric y Yanniel: - Esta BD es de prueba
A77: DB-008 | B77: SRV-026 | C77: BAC_DM | D77: SQL Server 2008/R2 | E77: OFFLINE | F77: 3408.01 | G77: 44602.169 | I77: D: | J77: Staging/UAT | K77: Low | L77: Yanniel / Eric / Grass | M77: N/A | N77: Yanniel | O77: N/A | P77: N/A | Q77: N/A | R77: Retire | S77: Decommission | T77: Technical Documentation | U77: Meeting del 2026-07-22 con Eric y Yanniel: - Esta BD es muy antigua o sin uso
A78: DB-009 | B78: SRV-026 | C78: BACMasterDB | D78: SQL Server 2008/R2 | E78: ONLINE | F78: 162.19 | G78: 7/14/2026 3:51 | H78: I:\SQL Databases\BACMasterDB.mdf | I78: F:\SQL Logs\BACMasterDB_log.ldf | J78: Pending validation | K78: Critical | L78: Yanniel / Eric / Grass | M78: ETL de actualización: - Proceso de cuando vienen las auditorías (FDIC u otro regulador): conteo de los reportes anteriores - Reportes de riesgo y de préstamo hipotecario (el ETL obtiene información de varios Excel, con cálculos que carga en varias tablas: y se exporta a un Excel y TXT) - Una o dos veces por año (depende de la auditoría) | N78: Yanniel | O78: Varios archivos Excel | R78: Pending analysis | S78: Pending validation | T78: Technical Documentation | U78: Meeting del 2026-07-22 con Eric y Yanniel: - Se usa muy pocas veces al año, tipicamente una o dos veces, excepcionalmente hasta tres, dependiendo de auditorias o requerimientos regulatorios.
A79: DB-010 | B79: SRV-026 | C79: BB_DocGen | D79: SQL Server 2016 | E79: ONLINE | F79: 80 | G79: 7/14/2026 3:51 | H79: I:\SQL Databases\BB_DocGen.mdf | I79: F:\SQL Logs\BB_DocGen_log.ldf | J79: Production | K79: Medium | L79: Andrés Paulino | M79: Proceso en COS - OnBoarding sys (COS) Instalación de Django (framework de python) para automatización de las formas | N79: Andrés Paulino | R79: Pending analysis | S79: Investigate | T79: Technical Owner | U79: Meeting del 2026-07-22 con Eric y Yanniel: - Eric aclaro que si se esta utilizando y que esta en produccion. Explico que la base esta relacionada con un proceso de CEO / COS / Onboarding - acronimo a validar - y sirve para generar documentacion automatica o formularios automaticos. - Tecnologia asociada: Django / Python framework. - Funcion: generacion de forms o documentacion automatica. - Relacion: extension del sistema de onboarding. - Owner indicado: Andres Paulino. - Estado: productiva, en uso, no en proceso de migracion.
A80: DB-011 | B80: SRV-026 | C80: BBFB_KATABAT_PROD | D80: SQL Server 2016 | E80: ONLINE | F80: 144 | G80: 7/14/2026 3:51 | H80: C:\Program Files\Microsoft SQL Server\MSSQL13.MSSQLSERVER\MSSQL\DATA\BBFB_KATABAT_PROD.mdf | I80: C:\Program Files\Microsoft SQL Server\MSSQL13.MSSQLSERVER\MSSQL\DATA\BBFB_KATABAT_PROD_log.ldf | J80: Production | K80: High | L80: Yanniel / Eric | M80: KATABAT Portal Web: - Sistema de collection del banco (información para complementar que el Vendor requiere) Portal Web (KATABAT Contact Manager) para que los empleados del banco que trabajan con los contactos actualicen los contactos ETL de actualización: - Para actualizar la lista de los préstamos (cuando hay un loan nuevo) Script de exportación: - A archivos de texto y se envían por FTP hacia KATABAT | O80: Portal web | R80: Pending analysis | S80: Pending validation | T80: Technical Documentation | U80: Meeting del 2026-07-22 con Eric y Yanniel: - Relacionada a un sistema de Collections: Portal Web (KATABAT Contact Manager) para que los empleados del banco que trabajan con los contactos actualicen los contactos - Funcion: agregar, editar y mantener contactos asociados a prestamos. - Inputs: lista de prestamos, probablemente actualizada por ETL/job. Incluye prestamos hipotecarios y ciertos prestamos de Jack Henry. - Outputs: Script de exportacion que genera archivos TXT o CSV. - Destino: Envio por SFTP al sistema del vendor, que luego consume los archivos. en este caso.
A81: DB-012 | B81: SRV-026 | C81: BBFB_WIRES | D81: SQL Server 2016 | E81: ONLINE | F81: 272 | G81: 7/14/2026 3:51 | H81: C:\Program Files\Microsoft SQL Server\MSSQL13.MSSQLSERVER\MSSQL\DATA\BFB_WIRES.mdf | I81: C:\Program Files\Microsoft SQL Server\MSSQL13.MSSQLSERVER\MSSQL\DATA\BFB_WIRES_log.ldf | J81: Production | K81: High | L81: Yanniel / Eric | M81: WIRES Reports - Existen tres tablas (una de las tablas ya no se utiliza: Direct_wire) Esto esta productivo: Hay un proceso que tiene que ver con los países de BSA ETL de exportacion / importacion - Importa informacion de Countries de la BD FEDLINK - Escribe en una tabla con la info de Countries, del Core Bancario (DB2) - Esta info finalmente es utilizada por el Departamenteo de BSA No esta en proceso de migracion por el momento | O81: WIRES de FEDLINK, archivos de Core Bancario | P81: Departamento de BSA (Bank Secrecy Act) | Q81: Departamento de BSA (Bank Secrecy Act) | R81: Pending analysis | S81: Pending validation | T81: Technical Documentation
A82: DB-013 | B82: SRV-026 | C82: BCP_Global_IBKR_prod | D82: SQL Server 2016 | E82: ONLINE | F82: 400 | G82: 7/14/2026 3:51 | H82: I:\SQL Databases\BCP_Global_IBKR_prod.mdf | I82: F:\SQL Logs\BCP_Global_IBKR_prod_log.ldf | J82: Production | K82: Medium | L82: Yanniel / Eric / Grass | M82: Information by IBKR Existe un API que se conecta a un servidor de Brasil Info de balances, clientes, etc. Una o dos veces al dia Cuatro tablas: cuentas, particpantes de las cuentas, balance historico de las cuentas, historicos de data de clientes | P82: Reportes diarios y mensuales que se envian a Brasil con informacion de las cuentas, los clientes, las inversiones, los balances Metricas mensuales | R82: Pending analysis | S82: Pending validation | T82: Technical Documentation | U82: Consume by DW
A83: DB-014 | B83: SRV-026 | C83: BCP_Global_IBKR_stage | D83: SQL Server 2016 | E83: ONLINE | F83: 4560 | G83: 7/14/2026 3:51 | H83: I:\SQL Databases\BCP_Global_IBKR_stage.mdf | I83: F:\SQL Logs\BCP_Global_IBKR_stage_log.ldf | J83: Staging/UAT | K83: Medium | M83: Information by IBKR | R83: Pending analysis | T83: Technical Documentation | U83: Consume by DW
A84: DB-015 | B84: SRV-026 | C84: BFB_MISC | D84: SQL Server 2008/R2 | E84: ONLINE | F84: 147 | G84: 7/14/2026 3:51 | H84: I:\SQL Databases\BFB_MISC.mdf | I84: F:\SQL Logs\BFB_MISC_1.ldf | J84: Production | K84: High | L84: Yanniel / Eric | M84: En produccion: temporary storage de los mortgage loans (prestamos hipotecarios), al principio del mes ETL: - lectura de los reportes de DMI (thirt party) - extraccion en el formato requerido para la app ASSIST ETL: Se lee del Core Bancario las cuentas digitales que se abren durante el dia y se cargan en una tabla. Y se extraen las del dia en un Excel, en una carpeta para un proceso posterior de validacion y enrole automatico de aquellas cuentas que no estan registradas (en banca en linea) | Q84: ASSIST APP Enrole automatico en banca en linea | R84: Pending analysis | S84: Pending validation | T84: Technical Documentation | U84: Consolidated: sum of the 2 source rows (data + log files) for this database in the original export.
A85: DB-016 | B85: SRV-026 | C85: BFI_INTG_prod | D85: SQL Server 2016 | E85: ONLINE | F85: 16 | G85: 7/14/2026 3:51 | H85: I:\SQL Databases\BFI_INTG_prod.mdf | I85: F:\SQL Logs\BFI_INTG_prod_log.ldf | J85: Pending validation | L85: Juan Grass | M85: Sistema de puntos | R85: Pending analysis | S85: Investigate | T85: Technical Documentation | U85: Consolidated: sum of the 2 source rows (data + log files) for this database in the original export.
A86: DB-017 | B86: SRV-026 | C86: BFI_INTG_stage | D86: SQL Server 2016 | E86: ONLINE | F86: 16 | G86: 7/14/2026 3:51 | H86: I:\SQL Databases\BFI_INTG_stage.mdf | I86: F:\SQL Logs\BFI_INTG_stage_log.ldf | J86: Staging/UAT | L86: Juan Grass | M86: Sistema de puntos | R86: Pending analysis | S86: Investigate | T86: Technical Documentation | U86: Consolidated: sum of the 2 source rows (data + log files) for this database in the original export.
A87: DB-018 | B87: SRV-026 | C87: BRAD_RISK_RPRT | D87: SQL Server 2008/R2 | E87: OFFLINE | F87: 4922.69 | G87: 44193.002 | I87: C: | J87: Pending validation | R87: Pending analysis | T87: Technical Documentation | U87: Consolidated: sum of the 2 source rows (data + log files) for this database in the original export.
A88: DB-019 | B88: SRV-026 | C88: BRAD_RPRT | D88: SQL Server 2008/R2 | E88: ONLINE | F88: 56549.25 | G88: 7/14/2026 3:51 | H88: I:\SQL Databases\BRAD_RPRT.mdf | I88: F:\SQL Logs\BRAD_RPRT.ldf | J88: Production | K88: Medium | L88: Yanniel / Eric | M88: Reportes de SSRS, de los BR: tentativamente esta live Tabla interest_income_eom .. Se esta utilizando por un Reporte La mayor parte de la informacion de esta BD esta migrada | Q88: Business Intelligence | R88: Pending analysis | S88: Pending validation | T88: Technical Documentation | U88: Consolidated: sum of the 2 source rows (data + log files) for this database in the original export.
A89: DB-020 | B89: SRV-026 | C89: BRAD_RPRT_dev | D89: SQL Server 2008/R2 | E89: ONLINE | F89: 30216.38 | G89: 7/14/2026 3:51 | H89: I:\SQL Databases\BRAD_RPRT_dev.mdf | I89: F:\SQL Logs\[BRAD_RPRT_dev].ldf | J89: Development | R89: Pending analysis | T89: Technical Documentation | U89: Consolidated: sum of the 2 source rows (data + log files) for this database in the original export.
A90: DB-021 | B90: SRV-026 | C90: BRAD_RPRT_stage | D90: SQL Server 2008/R2 | E90: ONLINE | F90: 406.13 | G90: 7/14/2026 3:51 | H90: I:\SQL Databases\BRAD_RPRT_stage.mdf | I90: F:\SQL Logs\[BRAD_RPRT_stage].ldf | J90: Staging/UAT | R90: Pending analysis | T90: Technical Documentation | U90: Consolidated: sum of the 2 source rows (data + log files) for this database in the original export.
A91: DB-022 | B91: SRV-026 | C91: Consolidated_Reports_Stage | D91: SQL Server 2016 | E91: ONLINE | F91: 6672 | G91: 7/14/2026 3:51 | H91: I:\SQL Databases\Consolidated_Reports_Stage.mdf | I91: F:\SQL Logs\Consolidated_Reports_Stage_log.ldf | J91: Staging/UAT | R91: Pending analysis | T91: Technical Documentation | U91: Consolidated: sum of the 2 source rows (data + log files) for this database in the original export.
A92: DB-023 | B92: SRV-026 | C92: Consolidated_Statements | D92: SQL Server 2016 | E92: ONLINE | F92: 17488 | G92: 7/14/2026 3:51 | H92: I:\SQL Databases\Consolidated_Statements.mdf | I92: F:\SQL Logs\Consolidated_Statements_log.ldf | J92: Production | K92: Critical | M92: ETL de importacion: - origen de datos: core bancario y Pershing - Info de Consolidated View y genera un reporte mensual con el estado de cuenta consolidado de clientes (Proceso automatizado remoto) - Este estado se publica mediante un API para los clientes en la banca en linea - Esta en proceso de migracion de plataforma que realiza algo similar (estimado para fin de anno) | Q92: Banca en Linea | R92: Pending analysis | T92: Technical Documentation | U92: Consolidated: sum of the 2 source rows (data + log files) for this database in the original export.
A93: DB-024 | B93: SRV-026 | C93: Dev_BBDesk | D93: SQL Server 2016 | E93: ONLINE | F93: 16 | G93: 7/14/2026 3:51 | H93: I:\SQL Databases\Dev_BBDesk.mdf | I93: F:\SQL Logs\Dev_BBDesk_log.ldf | J93: Pending validation | R93: Pending analysis | T93: Technical Documentation | U93: Consolidated: sum of the 2 source rows (data + log files) for this database in the original export.
A94: DB-025 | B94: SRV-026 | C94: EAA_PROD | D94: SQL Server 2016 | E94: ONLINE | F94: 16 | G94: 7/14/2026 3:51 | H94: I:\SQL Databases\EAA_PROD.mdf | I94: F:\SQL Logs\EAA_PROD_log.ldf | J94: Pending validation | R94: Pending analysis | T94: Technical Documentation | U94: Consolidated: sum of the 2 source rows (data + log files) for this database in the original export.
A95: DB-026 | B95: SRV-026 | C95: EAA_staging | D95: SQL Server 2016 | E95: ONLINE | F95: 16 | G95: 7/14/2026 3:51 | H95: I:\SQL Databases\EAA_staging.mdf | I95: F:\SQL Logs\EAA_staging_log.ldf | J95: Staging/UAT | R95: Pending analysis | T95: Technical Documentation | U95: Consolidated: sum of the 2 source rows (data + log files) for this database in the original export.
A96: DB-027 | B96: SRV-026 | C96: EWF_DB | D96: SQL Server 2008/R2 | E96: ONLINE | F96: 13.44 | G96: 7/14/2026 3:51 | H96: I:\SQL Databases\WTDB.mdf | I96: F:\SQL Logs\WTDB_log.ldf | J96: Pending validation | R96: Pending analysis | T96: Technical Documentation | U96: Consolidated: sum of the 2 source rows (data + log files) for this database in the original export.
A97: DB-028 | B97: SRV-026 | C97: INNOVA_ADI | D97: SQL Server 2008/R2 | E97: ONLINE | F97: 26.81 | G97: 7/14/2026 3:51 | H97: I:\SQL Databases\INNOVA_ADI.mdf | I97: F:\SQL Logs\INNOVA_ADI_log.ldf | J97: Pending validation | R97: Pending analysis | S97: Decommission | T97: Technical Documentation | U97: Consolidated: sum of the 2 source rows (data + log files) for this database in the original export.
A98: DB-029 | B98: SRV-026 | C98: INSIDERS_NSF_PROD | D98: SQL Server 2016 | E98: ONLINE | F98: 16 | G98: 7/14/2026 3:51 | H98: I:\SQL Databases\INSIDERS_NSF_PROD.mdf | I98: F:\SQL Logs\INSIDERS_NSF_PROD_log.ldf | J98: Pending validation | R98: Pending analysis | T98: Technical Documentation | U98: Consolidated: sum of the 2 source rows (data + log files) for this database in the original export.
A99: DB-030 | B99: SRV-026 | C99: MFTFA_DB_PROD | D99: SQL Server 2016 | E99: ONLINE | F99: 2256 | G99: 7/14/2026 3:51 | H99: I:\SQL Databases\MFTFA_DB_PROD.mdf | I99: F:\SQL Logs\MFTFA_DB_PROD_log.ldf | J99: Pending validation | R99: Pending analysis | T99: Technical Documentation | U99: Consolidated: sum of the 2 source rows (data + log files) for this database in the original export.
A100: DB-031 | B100: SRV-026 | C100: MFTFA_DB_Stage | D100: SQL Server 2016 | E100: ONLINE | F100: 14288 | G100: 7/14/2026 3:51 | H100: I:\SQL Databases\MFTFA_DB_Stage.mdf | I100: F:\SQL Logs\MFTFA_DB_Stage_log.ldf | J100: Staging/UAT | R100: Pending analysis | T100: Technical Documentation | U100: Consolidated: sum of the 2 source rows (data + log files) for this database in the original export.
A101: DB-032 | B101: SRV-026 | C101: PERSHING_DATA_PROD | D101: SQL Server 2016 | E101: ONLINE | F101: 66448 | G101: 7/14/2026 3:51 | H101: I:\SQL Databases\PERSHING_DATA_PROD.mdf | I101: F:\SQL Logs\PERSHING_DATA_PROD_log.ldf | J101: Production | K101: High | L101: Yanniel / Eric / Grass | M101: ETL de ingesta: - SSIS para descargar los archivos del FTP/SFTP de Pershing + procesamiento de archivos complejos o parsing no trivial con Python + persistencia en tablas SQL + scheduling en business days ETL de exportación hacia BB_DATA: - SSIS para exportar los datos desde PERSHING_DATA_PROD hacia BB_DATA (servidor BB-VV-BD-001) ETL de exportación hacia el Core Bancario (Jack Henry): - SSIS para exportar la data de inversiones + conexión ODBC con DB2 (AS400) + inyección en tablas temporales ETL de generación del Consolidated View (perfil consolidado de la Banca Online - Q2): - Se colecta información de cuentas e inversiones de clientes en distintos sistemas (reune balances, productos y tipos de productos) + persistencia en una tabla SQL: esto es consumido por un API | N101: Pershing | O101: Pershing (Investment Platform) - genera archivos TXT y los deja disponibles en un servidor FTP/SFTP | Q101: BB_DATA, Jack Henry (Data de Inversiones), Perfil Consolidado de la Banca Online (a través de un API) | R101: Pending analysis | S101: Investigate | T101: Technical Owner | U101: Meeting del 2026-07-22 con Eric y Yanniel: - PERSHING_DATA_PROD corresponde a un proceso legacy: el equipo tiene actualmente dos procesos relacionados con la importacion de datos de Pershing: un proceso legacy y un proceso mas nuevo relacionado con DW. - Pershing corresponde a inversiones, por lo que se usa como third party application data dentro del ecosistema Jack Henry. El core bancario es Jack Henry, asociado a AS400 y datos en DB2. Tambien se explico que Experience es la interfaz grafica / portal de Jack Henry. Jack Henry maneja principalmente datos bancarios retail, como cuentas de deposito, CDs, demand deposits, loans y productos bancarios tradicionales. - Existe la intencion de migrar o reemplazar este proceso legacy apuntando a DW. El nuevo enfoque seria que DW procese directamente los archivos TXT de Pershing, en lugar de consumir la base legacy actual. Una vez que el proceso este en DW, los procesos que hoy apuntan a PERSHING_DATA_PROD deberian modificarse para apuntar al nuevo origen. No se dio una fecha exacta. - ETL de generación del Consolidated View (perfil consolidado de la Banca Online - Q2): no está en proceso de migración por el momento
A102: DB-033 | B102: SRV-026 | C102: PERSHING_DATA_STAGE | D102: SQL Server 2016 | E102: ONLINE | F102: 8272 | G102: 7/14/2026 3:51 | H102: I:\SQL Databases\PERSHING_DATA_STAGE.mdf | I102: F:\SQL Logs\PERSHING_DATA_STAGE_log.ldf | J102: Staging/UAT | L102: Yanniel / Eric / Grass | R102: Pending analysis | S102: Pending validation | T102: Technical Documentation | U102: Consolidated: sum of the 2 source rows (data + log files) for this database in the original export.
A103: DB-036 | B103: SRV-026 | C103: RM_RO | D103: SQL Server 2016 | E103: ONLINE | F103: 16 | G103: 45643.177 | I103: C: | J103: Pending validation | R103: Pending analysis | T103: Technical Documentation | U103: Consolidated: sum of the 2 source rows (data + log files) for this database in the original export.
A104: DB-038 | B104: SRV-026 | C104: TRANSACT_prod | D104: SQL Server 2008/R2 | E104: ONLINE | F104: 1737.31 | G104: 7/14/2026 3:51 | H104: I:\SQL Databases\TRANSACT.mdf | I104: F:\SQL Logs\TRANSACT_log.ldf | J104: Production | L104: Juan Grass | M104: M2M - APPLICATION TRANSACT | R104: Pending analysis | S104: Investigate | T104: Technical Documentation | U104: Consolidated: sum of the 2 source rows (data + log files) for this database in the original export.
A105: DB-039 | B105: SRV-026 | C105: TRANSACT_stage | D105: SQL Server 2008/R2 | E105: ONLINE | F105: 165.75 | G105: 7/14/2026 3:51 | H105: I:\SQL Databases\TRANSACT_STAGE.mdf | I105: F:\SQL Logs\TRANSACT_STAGE_log.ldf | J105: Pending validation | R105: Pending analysis | T105: Technical Documentation | U105: Consolidated: sum of the 2 source rows (data + log files) for this database in the original export.
A106: DB-126 | B106: SRV-029 | C106: ALERT_FILE_DB | D106: SQL Server 2019 | E106: ONLINE | F106: 1004.69 | G106: 7/14/2026 3:17 | H106: C:\Program Files\Microsoft SQL Server\MSSQL16.MSSQLSERVER\MSSQL\DATA\ALERT_FILE_DB.mdf | I106: C:\Program Files\Microsoft SQL Server\MSSQL16.MSSQLSERVER\MSSQL\DATA\ALERT_FILE_DB_log.ldf | J106: Pending validation | R106: Pending analysis | T106: Linked Server SQL
A107: DB-127 | B107: SRV-029 | C107: ASSIST_IMP_RPTS | D107: SQL Server 2019 | E107: ONLINE | F107: 77456.31 | G107: 7/14/2026 3:17 | H107: C:\Program Files\Microsoft SQL Server\MSSQL16.MSSQLSERVER\MSSQL\DATA\ASSIST_IMP_RPTS.mdf | I107: C:\Program Files\Microsoft SQL Server\MSSQL16.MSSQLSERVER\MSSQL\DATA\ASSIST_IMP_RPTS_log.ldf | J107: Pending validation | R107: Pending analysis | T107: Linked Server SQL
A108: DB-128 | B108: SRV-029 | C108: LIVELO | D108: SQL Server 2019 | E108: ONLINE | F108: 2982 | G108: 7/14/2026 3:17 | H108: F:\Microsoft SQL Server\MSSQL15\DATA\LIVELO.mdf | I108: F:\Microsoft SQL Server\MSSQL15\DATA\LIVELO_log.ldf | J108: Pending validation | R108: Pending analysis | T108: Linked Server SQL
A109: DB-129 | B109: SRV-029 | C109: MISC | D109: SQL Server 2019 | E109: ONLINE | F109: 176 | G109: 7/14/2026 3:17 | H109: C:\Program Files\Microsoft SQL Server\MSSQL16.MSSQLSERVER\MSSQL\DATA\misc.mdf | I109: C:\Program Files\Microsoft SQL Server\MSSQL16.MSSQLSERVER\MSSQL\DATA\misc_log.ldf | J109: Pending validation | R109: Pending analysis | T109: Linked Server SQL
A110: DB-072 | B110: SRV-036 | C110: DWConfiguration | D110: SQL Server 2019 | E110: ONLINE | J110: Pending validation | R110: Pending analysis | T110: SQL Server Access | U110: Discovered from SSMS; compatibility level, size, backup and drive pending SQL query.
A111: DB-073 | B111: SRV-036 | C111: DWDiagnostics | D111: SQL Server 2019 | E111: ONLINE | J111: Pending validation | R111: Pending analysis | T111: SQL Server Access | U111: Discovered from SSMS; compatibility level, size, backup and drive pending SQL query.
A112: DB-074 | B112: SRV-036 | C112: DWQueue | D112: SQL Server 2019 | E112: ONLINE | J112: Pending validation | R112: Pending analysis | T112: SQL Server Access | U112: Discovered from SSMS; compatibility level, size, backup and drive pending SQL query.
A113: DB-075 | B113: SRV-036 | C113: JX-AppFab-Persistence | D113: SQL Server 2019 | E113: ONLINE | F113: 84.31 | G113: 7/13/2026 23:26 | H113: E:\Data\JX-AppFab-Persistence.mdf | I113: E:\Log\JX-AppFab-Persistence_log.ldf | J113: Pending validation | R113: Pending analysis | T113: SQL Server Access | U113: Discovered from SSMS; compatibility level, size, backup and drive pending SQL query.
A114: DB-076 | B114: SRV-036 | C114: JX-AppFab-Persistence2 | D114: SQL Server 2019 | E114: ONLINE | J114: Pending validation | R114: Pending analysis | T114: SQL Server Access | U114: Discovered from SSMS; compatibility level, size, backup and drive pending SQL query.
A115: DB-077 | B115: SRV-036 | C115: WFServer | D115: SQL Server 2019 | E115: ONLINE | J115: Pending validation | R115: Pending analysis | T115: SQL Server Access | U115: Discovered from SSMS; compatibility level, size, backup and drive pending SQL query.
A116: DB-078 | B116: SRV-036 | C116: WFServerReporting | D116: SQL Server 2019 | E116: ONLINE | J116: Pending validation | R116: Pending analysis | T116: SQL Server Access | U116: Discovered from SSMS; compatibility level, size, backup and drive pending SQL query.
A117: DB-131 | B117: SRV-052 | C117: AS400_STAGE | D117: SQL Server 2019 | E117: ONLINE | F117: 528 | G117: 7/14/2026 3:57 | H117: C:\Program Files\Microsoft SQL Server\MSSQL15.MSSQLSERVER\MSSQL\DATA\AS400_STAGE.mdf | I117: C:\Program Files\Microsoft SQL Server\MSSQL15.MSSQLSERVER\MSSQL\DATA\AS400_STAGE_log.ldf | J117: Pending validation | R117: Pending analysis | T117: Linked Server SQL
A118: DB-132 | B118: SRV-052 | C118: AXIOM_STAGE | D118: SQL Server 2019 | E118: ONLINE | F118: 144 | G118: 7/14/2026 3:57 | H118: C:\Program Files\Microsoft SQL Server\MSSQL13.MSSQLSERVER\MSSQL\DATA\AXIOM_STAGE.mdf | I118: C:\Program Files\Microsoft SQL Server\MSSQL13.MSSQLSERVER\MSSQL\DATA\AXIOM_STAGE_log.ldf | J118: Pending validation | R118: Pending analysis | T118: Linked Server SQL
A119: DB-133 | B119: SRV-052 | C119: B2BTXWEBAPP_STAGE | D119: SQL Server 2019 | E119: ONLINE | F119: 10.75 | G119: 7/14/2026 3:57 | H119: C:\Program Files\Microsoft SQL Server\MSSQL13.MSSQLSERVER\MSSQL\DATA\B2BTXWEBAPP_STAGE.mdf | I119: C:\Program Files\Microsoft SQL Server\MSSQL13.MSSQLSERVER\MSSQL\DATA\B2BTXWEBAPP_STAGE_log.ldf | J119: Pending validation | R119: Pending analysis | T119: Linked Server SQL
A120: DB-134 | B120: SRV-052 | C120: BAC_BRAD | D120: SQL Server 2019 | E120: ONLINE | F120: 1296.88 | G120: 7/14/2026 3:57 | H120: C:\Program Files\Microsoft SQL Server\MSSQL13.MSSQLSERVER\MSSQL\DATA\BAC_BRAD.mdf | I120: C:\Program Files\Microsoft SQL Server\MSSQL13.MSSQLSERVER\MSSQL\DATA\BAC_BRAD_log.ldf | J120: Pending validation | R120: Pending analysis | T120: Linked Server SQL
A121: DB-135 | B121: SRV-052 | C121: BAC_BRAD_premigration | D121: SQL Server 2019 | E121: ONLINE | F121: 4244 | G121: 7/14/2026 3:57 | H121: C:\Program Files\Microsoft SQL Server\MSSQL13.MSSQLSERVER\MSSQL\DATA\BAC_BRAD_premigration | I121: C:\Program Files\Microsoft SQL Server\MSSQL13.MSSQLSERVER\MSSQL\DATA\BAC_BRAD_premigration_log | J121: Pending validation | R121: Pending analysis | T121: Linked Server SQL
A122: DB-136 | B122: SRV-052 | C122: BAC_BRAD_PREPROD_060123 | D122: SQL Server 2019 | E122: ONLINE | F122: 3540 | G122: 7/14/2026 3:57 | H122: C:\Program Files\Microsoft SQL Server\MSSQL13.MSSQLSERVER\MSSQL\DATA\BAC_BRAD_PREPROD_060123 | I122: C:\Program Files\Microsoft SQL Server\MSSQL13.MSSQLSERVER\MSSQL\DATA\BAC_BRAD_PREPROD_060123_log | J122: Pending validation | R122: Pending analysis | T122: Linked Server SQL
A123: DB-137 | B123: SRV-052 | C123: BAC_BRAD_preprod_HML | D123: SQL Server 2019 | E123: ONLINE | F123: 2128 | G123: 7/14/2026 3:57 | H123: C:\Program Files\Microsoft SQL Server\MSSQL13.MSSQLSERVER\MSSQL\DATA\BAC_BRAD_preprod_HML.mdf | I123: C:\Program Files\Microsoft SQL Server\MSSQL13.MSSQLSERVER\MSSQL\DATA\BAC_BRAD_preprod_HML_log.ldf | J123: Pending validation | R123: Pending analysis | T123: Linked Server SQL
A124: DB-138 | B124: SRV-052 | C124: BAC_BRAD_STAGE | D124: SQL Server 2019 | E124: ONLINE | F124: 2772 | G124: 7/14/2026 3:57 | H124: C:\Program Files\Microsoft SQL Server\MSSQL13.MSSQLSERVER\MSSQL\DATA\BAC_BRAD_STAGE | I124: C:\Program Files\Microsoft SQL Server\MSSQL13.MSSQLSERVER\MSSQL\DATA\BAC_BRAD_STAGE_log | J124: Pending validation | R124: Pending analysis | T124: Linked Server SQL
A125: DB-139 | B125: SRV-052 | C125: BAC_Collections | D125: SQL Server 2019 | E125: ONLINE | F125: 40220.81 | G125: 7/14/2026 3:42 | H125: C:\Program Files\Microsoft SQL Server\MSSQL15.MSSQLSERVER\MSSQL\DATA\BAC_Collections.mdf | I125: C:\Program Files\Microsoft SQL Server\MSSQL15.MSSQLSERVER\MSSQL\DATA\BAC_Collections_1.ldf | J125: Pending validation | R125: Pending analysis | T125: Linked Server SQL
A126: DB-140 | B126: SRV-052 | C126: BAC_DI | D126: SQL Server 2019 | E126: ONLINE | F126: 6521.94 | G126: 7/14/2026 3:57 | H126: C:\Program Files\Microsoft SQL Server\MSSQL13.MSSQLSERVER\MSSQL\DATA\BAC_DI.mdf | I126: C:\Program Files\Microsoft SQL Server\MSSQL13.MSSQLSERVER\MSSQL\DATA\BAC_DI_log.ldf | J126: Pending validation | R126: Pending analysis | T126: Linked Server SQL
A127: DB-141 | B127: SRV-052 | C127: BAC_DI_STAGE | D127: SQL Server 2019 | E127: ONLINE | F127: 15807.5 | G127: 7/14/2026 3:57 | H127: C:\Program Files\Microsoft SQL Server\MSSQL13.MSSQLSERVER\MSSQL\DATA\BAC_DI_STAGE.mdf | I127: C:\Program Files\Microsoft SQL Server\MSSQL13.MSSQLSERVER\MSSQL\DATA\BAC_DI_STAGE_log.ldf | J127: Pending validation | R127: Pending analysis | T127: Linked Server SQL
A128: DB-142 | B128: SRV-052 | C128: BACMASTERDB_STAGE | D128: SQL Server 2019 | E128: ONLINE | F128: 54.38 | G128: 7/14/2026 3:57 | H128: C:\Program Files\Microsoft SQL Server\MSSQL13.MSSQLSERVER\MSSQL\DATA\BACMASTERDB_STAGE.mdf | I128: C:\Program Files\Microsoft SQL Server\MSSQL13.MSSQLSERVER\MSSQL\DATA\BACMASTERDB_STAGE_log.ldf | J128: Pending validation | R128: Pending analysis | T128: Linked Server SQL
... A151: DB-168 | B151: SRV-052 | C151: WFServerReporting | D151: SQL Server 2019 | E151: ONLINE | F151: 272 | G151: 7/14/2026 3:42 | H151: C:\Program Files\Microsoft SQL Server\MSSQL15.MSSQLSERVER\MSSQL\DATA\WFServerReporting_Primary.mdf | I151: C:\Program Files\Microsoft SQL Server\MSSQL15.MSSQLSERVER\MSSQL\DATA\WFServerReporting_Primary.ldf | J151: Pending validation | R151: Pending analysis | T151: Linked Server SQL
A152: DB-079 | B152: SRV-053 | C152: DQP_BRONZE | D152: SQL Server 2022 | E152: ONLINE | F152: 551382.94 | G152: 7/14/2026 3:53 | H152: E:\MSSQLSERVER\MSSQL\Data\DQP_BRONZE.mdf | I152: F:\MSSQLSERVER\MSSQL\Log\DQP_BRONZE_log.ldf | J152: Production | M152: DBT | R152: Pending analysis | T152: SQL Server Access | U152: Discovered from SSMS; compatibility level, size, backup and drive pending SQL query.
A153: DB-080 | B153: SRV-053 | C153: DQP_CONTROL | D153: SQL Server 2022 | E153: ONLINE | F153: 336 | G153: 7/14/2026 3:53 | H153: E:\MSSQLSERVER\MSSQL\Data\DQP_CONTROL.mdf | I153: F:\MSSQLSERVER\MSSQL\Log\DQP_CONTROL_log.ldf | J153: Production | M153: DBT | R153: Pending analysis | T153: SQL Server Access | U153: Discovered from SSMS; compatibility level, size, backup and drive pending SQL query.
A154: DB-081 | B154: SRV-053 | C154: DQP_GOLD | D154: SQL Server 2022 | E154: ONLINE | F154: 108624 | G154: 7/14/2026 3:53 | H154: E:\MSSQLSERVER\MSSQL\Data\DQP_GOLD.mdf | I154: F:\MSSQLSERVER\MSSQL\Log\DQP_GOLD_log.ldf | J154: Production | M154: DBT | R154: Pending analysis | T154: SQL Server Access | U154: Discovered from SSMS; compatibility level, size, backup and drive pending SQL query.
A155: DB-082 | B155: SRV-053 | C155: DQP_LANDING | D155: SQL Server 2022 | E155: ONLINE | F155: 189328 | G155: 7/14/2026 3:53 | H155: E:\MSSQLSERVER\MSSQL\Data\DQP_LANDING.mdf | I155: F:\MSSQLSERVER\MSSQL\Log\DQP_LANDING_log.ldf | J155: Production | M155: DBT | R155: Pending analysis | T155: SQL Server Access | U155: Discovered from SSMS; compatibility level, size, backup and drive pending SQL query.
A156: DB-083 | B156: SRV-053 | C156: DQP_SANDBOX | D156: SQL Server 2022 | E156: ONLINE | J156: Development | M156: DBT | R156: Pending analysis | T156: SQL Server Access | U156: Discovered from SSMS; compatibility level, size, backup and drive pending SQL query.
A157: DB-084 | B157: SRV-053 | C157: DQP_SILVER | D157: SQL Server 2022 | E157: ONLINE | F157: 833384 | G157: 7/14/2026 3:53 | H157: E:\MSSQLSERVER\MSSQL\Data\DQP_SILVER.mdf | I157: F:\MSSQLSERVER\MSSQL\Log\DQP_SILVER_log.ldf | J157: Production | M157: DBT | R157: Pending analysis | T157: SQL Server Access | U157: Discovered from SSMS; compatibility level, size, backup and drive pending SQL query.
A158: DB-125 | B158: SRV-054 | C158: DigitalBanking_PROD | D158: SQL Server 2019 | E158: ONLINE | F158: 1408 | G158: 7/14/2026 4:04 | H158: D:\MSSQLSERVER\MSSQL\Data\DigitalBanking_PROD.mdf | I158: E:\MSSQLSERVER\MSSQL\Log\DigitalBanking_PROD_log.ldf | J158: Pending validation | R158: Pending analysis | T158: Linked Server SQL
A159: DB-130 | B159: SRV-055 | C159: FEDLINK | D159: SQL Server 2019 | E159: ONLINE | F159: 68789.69 | G159: 7/14/2026 3:04 | H159: D:\Program Files\Microsoft SQL Server\MSSQL15.MSSQLSERVER\MSSQL\DATA\Fedlink.mdf | I159: E:\Program Files\Microsoft SQL Server\MSSQL15.MSSQLSERVER\MSSQL\Data\Fedlink_log.ldf | J159: Pending validation | R159: Pending analysis | T159: Linked Server SQL
...

Sheet 4. Dashboard
A1: Executive Dashboard
A3: =COUNTA('2. Servers'!A2:A200) -> 58 | C3: =COUNTIF('2. Servers'!H2:H200,"Yes") -> 48 | E3: =COUNTA('3. Databases'!A2:A291) -> 178 | G3: =ROUND(SUM('3. Databases'!F2:F291)/1024,1) -> 4032.5 | I3: =COUNTIF('2. Servers'!R2:R200,">0") -> 13 | K3: {=SUMPRODUCT(COUNTIF('Lists (Config)'!K4:K6,'3. Databases'!R2:R192))} -> 0 | M3: =COUNTIF('3. Databases'!R2:R192,"Pending analysis") -> 176
A4: Total Servers | C4: In Scope (MSSQL) | E4: Total Databases | G4: Total DB Size (GB) | I4: Servers with DBs | K4: Migration-Ready DBs | M4: DBs Pending Analysis
A6: Data on Template Servers | D6: Installed Engine Distribution (Servers) | G6: Server Review & Access
A7: Unknown | B7: =COUNTIF('2. Servers'!I2:Q58,"Unknown") -> 2 | D7: Microsoft SQL Server 2019 (64-bit) | E7: =COUNTIF('2. Servers'!$F$2:$F$200,$D7&"*") -> 19 | G7: Reviewed — Yes | H7: =COUNTIFS('2. Servers'!Q2:Q300,"Yes",'2. Servers'!$H$2:$H$300,"Yes") -> 2
A8: Empty | B8: =COUNTBLANK('2. Servers'!I2:Q58) -> 61 | D8: Microsoft SQL Server 2016 (64-bit) | E8: =COUNTIF('2. Servers'!$F$2:$F$200,$D8&"*") -> 11 | G8: Reviewed — No | H8: =COUNTIFS('2. Servers'!Q2:Q300,"No",'2. Servers'!$H$2:$H$300,"Yes") -> 46
A9: Complete | B9: =COUNTA('2. Servers'!I2:Q58) -> 452 | D9: MySQL Server 8.0 | E9: =COUNTIF('2. Servers'!$F$2:$F$200,$D9&"*") -> 5 | G9: Reviewed — Pending | H9: =C3-H7-H8 -> 0
D10: Microsoft SQL Server 2016 LocalDB | E10: =COUNTIF('2. Servers'!$F$2:$F$200,$D10&"*") -> 4 | G10: Access — Yes | H10: =COUNTIFS('2. Servers'!P2:P300,"Yes",'2. Servers'!$H$2:$H$300,"Yes") -> 7
A11: Servers by Environment (fill col I on Tab 2) | D11: Microsoft SQL Server Compact 4.0 SP1 x64 ENU | E11: =COUNTIF('2. Servers'!$F$2:$F$200,$D11&"*") -> 3 | G11: Access — No | H11: =COUNTIFS('2. Servers'!P2:P300,"No",'2. Servers'!$H$2:$H$300,"Yes") -> 41
A12: ='Lists (Config)'!A4 -> Production | B12: =COUNTIF('2. Servers'!$I$2:$I$301,$A12) -> 40 | D12: Microsoft SQL Server 2012 Express LocalDB | E12: =COUNTIF('2. Servers'!$F$2:$F$200,$D12&"*") -> 2 | G12: Access — Pending | H12: =C3-H11-H10 -> 0
A13: ='Lists (Config)'!A5 -> Staging/UAT | B13: =COUNTIF('2. Servers'!$I$2:$I$301,$A13) -> 4 | D13: Microsoft SQL Server Compact 3.5 SP2 ENU | E13: =COUNTIF('2. Servers'!$F$2:$F$200,$D13&"*") -> 2
A14: ='Lists (Config)'!A6 -> QA | B14: =COUNTIF('2. Servers'!$I$2:$I$301,$A14) -> 0 | D14: MySQL Server 5.7 | E14: =COUNTIF('2. Servers'!$F$2:$F$200,$D14&"*") -> 2 | G14: Databases per Server
A15: ='Lists (Config)'!A7 -> Development | B15: =COUNTIF('2. Servers'!$I$2:$I$301,$A15) -> 4 | D15: MongoDB 8.2.6 2008R2Plus SSL (64 bit) | E15: =COUNTIF('2. Servers'!$F$2:$F$200,$D15&"*") -> 1 | G15: Databases linked to a server | H15: {=SUMPRODUCT(('3. Databases'!A2:A291<>"")*('3. Databases'!B2:B291<>""))} -> 178
A16: ='Lists (Config)'!A8 -> DR | B16: =COUNTIF('2. Servers'!$I$2:$I$301,$A16) -> 9 | D16: Microsoft SQL Server 2012 (64-bit) | E16: =COUNTIF('2. Servers'!$F$2:$F$200,$D16&"*") -> 1 | G16: Servers hosting >1 DB | H16: =COUNTIF('2. Servers'!R2:R200,">1") -> 11
A17: ='Lists (Config)'!A9 -> Pending validation | B17: =COUNTIF('2. Servers'!$I$2:$I$301,$A17) -> 0 | D17: Microsoft SQL Server 2017 (64-bit) | E17: =COUNTIF('2. Servers'!$F$2:$F$200,$D17&"*") -> 1 | G17: Max DBs on one server | H17: =MAX('2. Servers'!R2:R200) -> 40
D18: Microsoft SQL Server Compact 4.0 x64 ENU | E18: =COUNTIF('2. Servers'!$F$2:$F$200,$D18&"*") -> 1 | G18: Avg DBs per hosting server | H18: =IFERROR(ROUND(SUM('2. Servers'!R2:R200)/COUNTIF('2. Servers'!R2:R200,">0"),1),0) -> 13.7
A19: Databases by Environment (fill col J on Tab 3) | D19: Mariadb-server | E19: =COUNTIF('2. Servers'!$F$2:$F$200,$D19&"*") -> 1
A20: ='Lists (Config)'!A4 -> Production | B20: =COUNTIF('3. Databases'!$J$2:$J$291,$A20) -> 17 | D20: MySQL Server 8.4 | E20: =COUNTIF('2. Servers'!$F$2:$F$200,$D20&"*") -> 1 | G20: Migration Status Distribution (Databases)
A21: ='Lists (Config)'!A5 -> Staging/UAT | B21: =COUNTIF('3. Databases'!$J$2:$J$291,$A21) -> 10 | D21: Microsoft SQL Server 2022 (64-bit) | E21: =COUNTIF('2. Servers'!$F$2:$F$200,$D21&"*") -> 4 | G21: ='Lists (Config)'!I4 -> Lift and Shift | H21: =COUNTIF('3. Databases'!$R$2:$R$291,$G21) -> 0
A22: ='Lists (Config)'!A6 -> QA | B22: =COUNTIF('3. Databases'!$J$2:$J$291,$A22) -> 0 | G22: ='Lists (Config)'!I5 -> Rehost | H22: =COUNTIF('3. Databases'!$R$2:$R$291,$G22) -> 0
A23: ='Lists (Config)'!A7 -> Development | B23: =COUNTIF('3. Databases'!$J$2:$J$291,$A23) -> 23 | D23: Database State | G23: ='Lists (Config)'!I6 -> Replatform | H23: =COUNTIF('3. Databases'!$R$2:$R$291,$G23) -> 0
A24: ='Lists (Config)'!A8 -> DR | B24: =COUNTIF('3. Databases'!$J$2:$J$291,$A24) -> 0 | D24: ONLINE | E24: =COUNTIF('3. Databases'!E2:E291,"ONLINE") -> 176 | G24: ='Lists (Config)'!I7 -> Refactor | H24: =COUNTIF('3. Databases'!$R$2:$R$291,$G24) -> 0
A25: ='Lists (Config)'!A9 -> Pending validation | B25: =COUNTIF('3. Databases'!$J$2:$J$291,$A25) -> 128 | D25: OFFLINE | E25: =COUNTIF('3. Databases'!E2:E291,"OFFLINE") -> 2 | G25: ='Lists (Config)'!I8 -> Repurchase | H25: =COUNTIF('3. Databases'!$R$2:$R$291,$G25) -> 0
G26: ='Lists (Config)'!I9 -> Retain | H26: =COUNTIF('3. Databases'!$R$2:$R$291,$G26) -> 0
A27: Owners | D27: Recomendations | G27: ='Lists (Config)'!I10 -> Retire | H27: =COUNTIF('3. Databases'!$R$2:$R$291,$G27) -> 2
A28: Technical Owners Servers | B28: =COUNTIFS('2. Servers'!$M$2:$M$300,"<>",'2. Servers'!$H$2:$H$300,"Yes") -> 47 | D28: ='Lists (Config)'!E4 -> Keep | E28: =COUNTIF('3. Databases'!$S$2:$S$491,$D28) -> 2 | G28: ='Lists (Config)'!I11 -> Pending analysis | H28: =COUNTIF('3. Databases'!$R$2:$R$291,$G28) -> 176
A29: Business Owners Servers | B29: =COUNTIFS('2. Servers'!$N$2:$N$300,"<>",'2. Servers'!$H$2:$H$300,"Yes") -> 39 | D29: ='Lists (Config)'!E5 -> Upgrade | E29: =COUNTIF('3. Databases'!$S$2:$S$491,$D29) -> 0 | G29: ='Lists (Config)'!I12 -> Blocked | H29: =COUNTIF('3. Databases'!$R$2:$R$291,$G29) -> 0
A30: Technical Owners Databases | B30: =COUNTIF('3. Databases'!$L$2:$L$490,"<>") -> 19 | D30: ='Lists (Config)'!E6 -> Consolidate | E30: =COUNTIF('3. Databases'!$S$2:$S$491,$D30) -> 0
A31: Sources Owners Databases | B31: =COUNTIF('3. Databases'!$O$2:$O$490,"<>") -> 9 | D31: ='Lists (Config)'!E7 -> Migrate | E31: =COUNTIF('3. Databases'!$S$2:$S$491,$D31) -> 0 | G31: Criticallity (Databases)
A32: Dependency Owners Databases | B32: =COUNTIF('3. Databases'!$P$2:$P$490,"<>") -> 7 | D32: ='Lists (Config)'!E8 -> Decommission | E32: =COUNTIF('3. Databases'!$S$2:$S$491,$D32) -> 5 | G32: ='Lists (Config)'!C4 -> Critical | H32: =COUNTIF('3. Databases'!$K$2:$K291,$G32) -> 3
D33: ='Lists (Config)'!E9 -> Investigate | E33: =COUNTIF('3. Databases'!$S$2:$S$491,$D33) -> 5 | G33: ='Lists (Config)'!C5 -> High | H33: =COUNTIF('3. Databases'!$K$2:$K292,$G33) -> 4
D34: ='Lists (Config)'!E10 -> Pending validation | E34: =COUNTIF('3. Databases'!$S$2:$S$491,$D34) -> 9 | G34: ='Lists (Config)'!C6 -> Medium | H34: =COUNTIF('3. Databases'!$K$2:$K293,$G34) -> 4
G35: ='Lists (Config)'!C7 -> Low | H35: =COUNTIF('3. Databases'!$K$2:$K294,$G35) -> 5
G36: ='Lists (Config)'!C8 -> Unknown | H36: =COUNTIF('3. Databases'!$K$2:$K295,$G36) -> 2
G37: ='Lists (Config)'!C9 -> Pending validation | H37: =COUNTIF('3. Databases'!$K$2:$K296,$G37) -> 0

Sheet 5. Questions
A1: ID | B1: Topic | C1: Question | D1: Owner | E1: Answer | F1: Status
A2: Q1 | B2: Duplicates / Engine | C2: For the duplicates, was the "engine" (product) taken into account when identifying them? | F2: Open
A3: Q2 | B3: Databases in Scope | C3: "No business databases found": does this mean the databases do not exist, that they are not used, or that Bradesco does not manage that server? For example, BACSANSRV has 23 DBs — who owns them and what are they for? | F3: Open
A4: Q3 | B4: Access & Ownership | C4: For the servers, how do we get access? Can access be granted? Do we need to escalate this somewhere? Can you identify all the DBs on that server? Is there an owner for each DB we can consult about how it is fed and what it is used for? | F4: Open
A5: Q4 | B5: Scope / SQL Compact | C5: Can we consider the SQL Compact instances out of scope because they contain no databases? If they do contain databases, are they used by applications? | F5: Open
A6: Q5 | B6: Data Quality | C6: We have an example: server BFBWEBDEV runs MSSQL 2019, but its note says "Non-MSSQL product detected". Which value is correct? | F6: Open
A7: Q6 | B7: HA / DR | C7: The HA/DR column is marked as DR: can we identify which server is its DR pair? For example, BBFBDBVIEW is marked as DR — which server does it serve as DR for, and what does it have as its DR? | F7: Open

Sheet 6. Glossary
A1: Term | B1: Definition
A2: MSSQL / SQL Server | B2: Microsoft SQL Server, the relational database management system (RDBMS) in scope for this assessment. Versions found in this inventory: 2008/R2, 2012, 2016, 2017, 2019, plus Express/LocalDB/Compact variants.
A3: Instance | B3: An independent installation of the SQL Server engine on a server. One server can host several instances, each with its own databases, logins and configuration.
A4: Database | B4: A named collection of data files (data + log) managed by an instance. One row on Tab 3 = one database.
A5: Backup | B5: A copy of a database (Full, Differential, or Transaction Log) used to recover data. 'Last Backup' on Tab 3 comes from the backup history.
A6: Restore | B6: The process of recovering a database from backups to the same or a different server; standard method for Lift and Shift migrations.
A7: Lift and Shift | B7: Migration approach: move the database as-is to the new platform without code changes. Counted as migration-ready.
A8: Rehost | B8: Same concept as Lift and Shift: change the hosting infrastructure (e.g. new VM) keeping engine and code unchanged. Migration-ready.
A9: Replatform | B9: Move to a different platform version/service (e.g. SQL 2008 → SQL 2019, or PaaS) with minimal changes. Migration-ready.
A10: Refactor | B10: Redesign application/database code to fit the target platform. Requires development effort; not migration-ready until done.
A11: Repurchase | B11: Replace the application with a different product (e.g. SaaS); the database is retired or converted.
A12: Retain | B12: Keep the database where it is for now (out of migration wave).
... A32: Recommendation | B32: The proposed action for a database on Tab 3 (e.g. Pending validation, Decommission), distinct from 'Migration Status'. Captures the assessor's suggested next step.
